{"delim_url": "https://askfred.net/Results/roundResults.php?event_id=159658&seq=2&highlight_competitor_id=", "tmt_id": "37443", "event_id": "159658", "rounds": [{"round_no": 1, "results": ["\u00a0(1)\u00a0Chai, Ethan : ", "\u00a0(16)\u00a0-Bye-", "\u00a0(9)\u00a0Fan, Anina : ", "\u00a0(8)\u00a0Chen, Max : ", "\u00a0(5)\u00a0Mu, Lening(Oliver) : ", "\u00a0(12)\u00a0-Bye-", "\u00a0(13)\u00a0-Bye-", "\u00a0(4)\u00a0Hu, Lucas : ", "\u00a0(3)\u00a0Gao, Cynthia : ", "\u00a0(14)\u00a0-Bye-", "\u00a0(11)\u00a0Lu, Scarlett : ", "\u00a0(6)\u00a0Su, Evelyn : ", "\u00a0(7)\u00a0Zhan, Nancy : ", "\u00a0(10)\u00a0Ma, Owen : ", "\u00a0(15)\u00a0-Bye-", "\u00a0(2)\u00a0Zhai, Avalo : "]}, {"round_no": 2, "results": ["\u00a0(1)\u00a0Chai, Ethan : ", "\u00a0(9)\u00a0Fan, Anina : ", "\u00a010 - 8", "\u00a0(5)\u00a0Mu, Lening(Oliver) : ", "\u00a0(4)\u00a0Hu, Lucas : ", "\u00a0(3)\u00a0Gao, Cynthia : ", "\u00a0(6)\u00a0Su, Evelyn : ", "\u00a06 - 10", "\u00a0(7)\u00a0Zhan, Nancy : ", "\u00a010 - 4", "\u00a0(2)\u00a0Zhai, Avalo : "]}, {"round_no": 3, "results": ["\u00a0(1)\u00a0Chai, Ethan : ", "\u00a010 - 2", "\u00a0(5)\u00a0Mu, Lening(Oliver) : ", "\u00a010 - 6", "\u00a0(6)\u00a0Su, Evelyn : ", "\u00a09 - 10", "\u00a0(2)\u00a0Zhai, Avalo : ", "\u00a04 - 10"]}, {"round_no": 4, "results": ["\u00a0(1)\u00a0Chai, Ethan : ", "\u00a010 - 3", "\u00a0(2)\u00a0Zhai, Avalo : ", "\u00a08 - 10"]}, {"round_no": 5, "results": ["\u00a0(1)\u00a0Chai, Ethan : ", "\u00a010 - 5"]}]}