{"delim_url": "https://askfred.net/Results/roundResults.php?event_id=148778&seq=2&highlight_competitor_id=", "tmt_id": "37520", "event_id": "148778", "rounds": [{"round_no": 1, "results": ["\u00a0(1)\u00a0Crotchett, Kaiden : ", "\u00a0(32)\u00a0-Bye-", "\u00a0(17)\u00a0Davis, Neil : ", "\u00a0(16)\u00a0Lee, Tobias : ", "\u00a0(9)\u00a0Volkmann, Daniel : ", "\u00a0(24)\u00a0Howard, Joel : ", "\u00a0(25)\u00a0Duchow, Matthew : ", "\u00a0(8)\u00a0Ameli, Sean : ", "\u00a0(5)\u00a0Frank, Timmy : ", "\u00a0(28)\u00a0Barnes, Drexell : ", "\u00a0(21)\u00a0Suvorov, Yuly : ", "\u00a0(12)\u00a0Duchow, Benjamin : ", "\u00a0(12)\u00a0Varney, John : ", "\u00a0(20)\u00a0Faubert, Andy : ", "\u00a0(29)\u00a0Lucas, Jeff : ", "\u00a0(4)\u00a0Rayle, Evan : ", "\u00a0(2)\u00a0Comes, Matthew : ", "\u00a0(30)\u00a0Comes, John : ", "\u00a0(19)\u00a0Milam, Hugh : ", "\u00a0(14)\u00a0Cranor, Erich : ", "\u00a0(11)\u00a0Bodon, Michele : ", "\u00a0(22)\u00a0Zutshi, Anshul : ", "\u00a0(27)\u00a0King, Dick : ", "\u00a0(6)\u00a0Carnahan, Garrett : ", "\u00a0(7)\u00a0Roy, Joseph : ", "\u00a0(26)\u00a0Rwamashongye, Alex : ", "\u00a0(23)\u00a0Deo, Ameya : ", "\u00a0(10)\u00a0Larsen, Samuel : ", "\u00a0(15)\u00a0Alger, Caleb : ", "\u00a0(18)\u00a0Frank, Fred : ", "\u00a0(31)\u00a0Beck, Brian : ", "\u00a0(2)\u00a0Lange, Henry : "]}, {"round_no": 2, "results": ["\u00a0(1)\u00a0Crotchett, Kaiden : ", "\u00a0(16)\u00a0Lee, Tobias : ", "\u00a07 - 15", "\u00a0(9)\u00a0Volkmann, Daniel : ", "\u00a015 - 6", "\u00a0(8)\u00a0Ameli, Sean : ", "\u00a013 - 15", "\u00a0(5)\u00a0Frank, Timmy : ", "\u00a015 - 3", "\u00a0(21)\u00a0Suvorov, Yuly : ", "\u00a014 - 13", "\u00a0(20)\u00a0Faubert, Andy : ", "\u00a09 - 15", "\u00a0(4)\u00a0Rayle, Evan : ", "\u00a07 - 15", "\u00a0(2)\u00a0Comes, Matthew : ", "\u00a015 - 1", "\u00a0(19)\u00a0Milam, Hugh : ", "\u00a015 - 12", "\u00a0(11)\u00a0Bodon, Michele : ", "\u00a015 - 11", "\u00a0(6)\u00a0Carnahan, Garrett : ", "\u00a06 - 15", "\u00a0(7)\u00a0Roy, Joseph : ", "\u00a015 - 10", "\u00a0(10)\u00a0Larsen, Samuel : ", "\u00a02 - 15", "\u00a0(15)\u00a0Alger, Caleb : ", "\u00a015 - 14", "\u00a0(2)\u00a0Lange, Henry : ", "\u00a08 - 15"]}, {"round_no": 3, "results": ["\u00a0(1)\u00a0Crotchett, Kaiden : ", "\u00a015 - 13", "\u00a0(9)\u00a0Volkmann, Daniel : ", "\u00a015 - 11", "\u00a0(5)\u00a0Frank, Timmy : ", "\u00a015 - 11", "\u00a0(20)\u00a0Faubert, Andy : ", "\u00a015 - 10", "\u00a0(2)\u00a0Comes, Matthew : ", "\u00a015 - 8", "\u00a0(6)\u00a0Carnahan, Garrett : ", "\u00a08 - 15", "\u00a0(10)\u00a0Larsen, Samuel : ", "\u00a08 - 15", "\u00a0(2)\u00a0Lange, Henry : ", "\u00a02 - 15"]}, {"round_no": 4, "results": ["\u00a0(1)\u00a0Crotchett, Kaiden : ", "\u00a015 - 14", "\u00a0(5)\u00a0Frank, Timmy : ", "\u00a015 - 9", "\u00a0(6)\u00a0Carnahan, Garrett : ", "\u00a014 - 15", "\u00a0(2)\u00a0Lange, Henry : ", "\u00a013 - 14"]}, {"round_no": 5, "results": ["\u00a0(5)\u00a0Frank, Timmy : ", "\u00a014 - 15", "\u00a0(6)\u00a0Carnahan, Garrett : ", "\u00a015 - 8"]}, {"round_no": 6, "results": ["\u00a0(6)\u00a0Carnahan, Garrett : ", "\u00a08 - 15"]}]}