{"delim_url": "https://askfred.net/Results/roundResults.php?event_id=154056&seq=2&highlight_competitor_id=", "tmt_id": "38743", "event_id": "154056", "rounds": [{"round_no": 1, "results": ["\u00a0(1)\u00a0Haro Lima, Elena Mercedes : ", "\u00a0(8)\u00a0-Bye-", "\u00a0(5)\u00a0Hu, Allison C. : ", "\u00a0(4)\u00a0Congiusta, Aelex : ", "\u00a0(3)\u00a0Hua, Catherine : ", "\u00a0(6)\u00a0Subu, Grace : ", "\u00a0(7)\u00a0Leake, Kaelyn : ", "\u00a0(2)\u00a0Rodriguez, Colette : ", "\u00a0(5)\u00a0Hu, Allison C. : ", "\u00a0(3)\u00a0Hua, Catherine : "]}, {"round_no": 2, "results": ["\u00a0(1)\u00a0Haro Lima, Elena Mercedes : ", "\u00a0(5)\u00a0Hu, Allison C. : ", "\u00a015 - 13", "\u00a0(3)\u00a0Hua, Catherine : ", "\u00a015 - 6", "\u00a0(2)\u00a0Rodriguez, Colette : ", "\u00a05 - 15", "\u00a0(3)\u00a0Hua, Catherine : ", "\u00a013 - 15"]}, {"round_no": 3, "results": ["\u00a0(1)\u00a0Haro Lima, Elena Mercedes : ", "\u00a015 - 8", "\u00a0(2)\u00a0Rodriguez, Colette : ", "\u00a012 - 15"]}, {"round_no": 4, "results": ["\u00a0(1)\u00a0Haro Lima, Elena Mercedes : ", "\u00a015 - 13"]}]}