{"delim_url": "https://askfred.net/Results/roundResults.php?event_id=159449&seq=2&highlight_competitor_id=", "tmt_id": "40096", "event_id": "159449", "rounds": [{"round_no": 1, "results": ["\u00a0(1)\u00a0Freedman, Janna : ", "\u00a0(16)\u00a0-Bye-", "\u00a0(9)\u00a0Hsiang, Melanie : ", "\u00a0(8)\u00a0Fu, Linqian (Helen) : ", "\u00a0(5)\u00a0Andres, Katherine : ", "\u00a0(12)\u00a0Koll-Bravmann, Ryder : ", "\u00a0(13)\u00a0Sosa, Elizabeth : ", "\u00a0(4)\u00a0Plonka, Kaley : ", "\u00a0(3)\u00a0Erikson, Kira : ", "\u00a0(14)\u00a0-Bye-", "\u00a0(11)\u00a0Andres, Charmaine : ", "\u00a0(6)\u00a0Fang, Victoria : ", "\u00a0(7)\u00a0Alcalde, Anneliesse : ", "\u00a0(10)\u00a0Panigrahi, Sophia : ", "\u00a0(15)\u00a0-Bye-", "\u00a0(2)\u00a0Patel, Riya : "]}, {"round_no": 2, "results": ["\u00a0(1)\u00a0Freedman, Janna : ", "\u00a0(9)\u00a0Hsiang, Melanie : ", "\u00a015 - 12", "\u00a0(5)\u00a0Andres, Katherine : ", "\u00a015 - 3", "\u00a0(4)\u00a0Plonka, Kaley : ", "\u00a02 - 15", "\u00a0(3)\u00a0Erikson, Kira : ", "\u00a0(6)\u00a0Fang, Victoria : ", "\u00a00 - 0", "\u00a0(7)\u00a0Alcalde, Anneliesse : ", "\u00a015 - 12", "\u00a0(2)\u00a0Patel, Riya : "]}, {"round_no": 3, "results": ["\u00a0(1)\u00a0Freedman, Janna : ", "\u00a015 - 5", "\u00a0(5)\u00a0Andres, Katherine : ", "\u00a015 - 4", "\u00a0(3)\u00a0Erikson, Kira : ", "\u00a015 - 11", "\u00a0(2)\u00a0Patel, Riya : ", "\u00a07 - 15"]}, {"round_no": 4, "results": ["\u00a0(1)\u00a0Freedman, Janna : ", "\u00a015 - 11", "\u00a0(2)\u00a0Patel, Riya : ", "\u00a014 - 15"]}, {"round_no": 5, "results": ["\u00a0(1)\u00a0Freedman, Janna : ", "\u00a015 - 6"]}]}