{"pool_url": "https://askfred.net/Results/roundResults.php?seq=1&event_id=149690", "tmt_id": "37708", "event_id": "149690", "pools": [{"pool_no": "Pool #1", "fencers": [{"name": " Howard, Megan : ", "pool_pos": "1", "results": ["D0", "D2", "D1", "D4"]}, {"name": " Oxenreider, Tierna : ", "pool_pos": "2", "results": ["V5", "V5", "V5", "V5"]}, {"name": " Anglin, Benjamin : ", "pool_pos": "3", "results": ["V5", "D2", "D4", "D2"]}, {"name": " Waters, Will : ", "pool_pos": "4", "results": ["V5", "D2", "V5", "D2"]}, {"name": " Nirode, David : ", "pool_pos": "5", "results": ["V5", "D1", "V5", "V5"]}]}, {"pool_no": "Pool #2", "fencers": [{"name": " Savini, Lorenza : ", "pool_pos": "1", "results": ["D3", "D3", "D2", "D4"]}, {"name": " Mason, Alex : ", "pool_pos": "2", "results": ["V5", "V5", "V5", "V5"]}, {"name": " Whited, Matthew : ", "pool_pos": "3", "results": ["V5", "D3", "D1", "D1"]}, {"name": " Visurakapalli, Sathvik : ", "pool_pos": "4", "results": ["V5", "D4", "V5", "V5"]}, {"name": " Knowles, Ethan : ", "pool_pos": "5", "results": ["V5", "D4", "V5", "D1"]}]}, {"pool_no": "Pool #3", "fencers": [{"name": " Silvania, Michael : ", "pool_pos": "1", "results": ["D2", "V5", "D1", "D0"]}, {"name": " Ayush, Shah : ", "pool_pos": "2", "results": ["V5", "V5", "V5", "D3"]}, {"name": " Bartch, Ethan : ", "pool_pos": "3", "results": ["D1", "D1", "D0", "D1"]}, {"name": " Hane, Matthew : ", "pool_pos": "4", "results": ["V5", "D2", "V5", "D2"]}, {"name": " Wojciechowski, Matthew : ", "pool_pos": "5", "results": ["V5", "V5", "V5", "V5"]}]}]}