{"pool_url": "https://askfred.net/Results/roundResults.php?event_id=157235&seq=2&highlight_competitor_id=", "tmt_id": "39493", "event_id": "157235", "pools": [{"pool_no": "Pool #1", "fencers": [{"name": " DeAngelo, Jack : ", "pool_pos": "1", "results": ["D3", "V5", "V5", "V5"]}, {"name": " Ursu, Marcel : ", "pool_pos": "2", "results": ["V5", "V5", "V5", "D1"]}, {"name": " Hallisay III, Vincent : ", "pool_pos": "3", "results": ["D0", "D4", "V5", "D0"]}, {"name": " Fonseca Maizel, Rio : ", "pool_pos": "4", "results": ["D1", "D2", "D3", "D1"]}, {"name": " Morgan, Abrahm : ", "pool_pos": "5", "results": ["D3", "V5", "V5", "V5"]}]}]}