{"pool_url": "https://askfred.net/Results/roundResults.php?seq=1&event_id=160445", "tmt_id": "40104", "event_id": "160445", "pools": [{"pool_no": "Pool #1", "fencers": [{"name": " Wang, Jolie : ", "pool_pos": "1", "results": ["V5", "D3", "V5", "V5", "D0", "D4"]}, {"name": " Glukhov, Grace : ", "pool_pos": "2", "results": ["D2", "V5", "D3", "D2", "D0", "D0"]}, {"name": " Yurkova, Mariia : ", "pool_pos": "3", "results": ["V5", "D4", "V5", "V5", "D0", "D3"]}, {"name": " Zeldin, Nadia : ", "pool_pos": "4", "results": ["D0", "V5", "D1", "D0", "D3", "D1"]}, {"name": " Yang, Iris : ", "pool_pos": "5", "results": ["D0", "V5", "D2", "V5", "D2", "D0"]}, {"name": " Goor, Viviene : ", "pool_pos": "6", "results": ["V5", "V5", "V5", "V5", "V5", "D2"]}, {"name": " Cascone, Emily : ", "pool_pos": "7", "results": ["V5", "V5", "V5", "V5", "V5", "V5"]}]}]}