{"tmt_name": "Jeff Wolfe Long Island Challenge ROC 2018", "tmt_id": "39958", "loc": "\nROCKY POINT, NY\n", "date": "\nApr 28 - Apr 29, 2018\n", "tmt_url": "https://askfred.net/Results/results.php?tournament_id=39958", "events": [{"event_name": ["\n", "Div 1A Senior Men's Epee:\u00a0\u00a0\u00a0\n53 Competitors, a A2 Event\n\u00a0\u00a0\u00a0\u00a0\u00a0\u00a0\n", "\n"], "event_id": "159026", "fencers": [{"place": "1", "fencer_name": "\u00a0\u00a0Stott, Donovan", "fencer_id": "115905", "club": "RFC", "rating": "A2018\u00a0", "rating_earned": "\u00a0"}, {"place": "2", "fencer_name": "\u00a0\u00a0Cummings, Atticus", "fencer_id": "113082", "club": "BOZEMAN", "rating": "A2018\u00a0", "rating_earned": "\u00a0"}, {"place": "3", "fencer_name": "\u00a0\u00a0White, Khristopher", "fencer_id": "65807", "club": "WESTBROOK", "rating": "C2016\u00a0", "rating_earned": "B2018\u00a0"}, {"place": "3", "fencer_name": "\u00a0\u00a0Yu, Colin", "fencer_id": "82928", "club": "MFA", "rating": "A2018\u00a0", "rating_earned": "\u00a0"}, {"place": "5", "fencer_name": "\u00a0\u00a0Ra, Daniel", "fencer_id": "92719", "club": "FC", "rating": "A2018\u00a0", "rating_earned": "\u00a0"}, {"place": "6", "fencer_name": "\u00a0\u00a0Kambeseles, Peter", "fencer_id": "97290", "club": "NYFA", "rating": "B2018\u00a0", "rating_earned": "\u00a0"}, {"place": "7", "fencer_name": "\u00a0\u00a0Krenz, Michal", "fencer_id": "122876", "club": "FAW", "rating": "B2017\u00a0", "rating_earned": "\u00a0"}, {"place": "8", "fencer_name": "\u00a0\u00a0Rogak, Ben", "fencer_id": "112672", "club": "MISSION FC", "rating": "B2018\u00a0", "rating_earned": "\u00a0"}, {"place": "9", "fencer_name": "\u00a0\u00a0Maisel, Simon F", "fencer_id": "69804", "club": "OLYMPIAFC", "rating": "B2017\u00a0", "rating_earned": "\u00a0"}, {"place": "10", "fencer_name": "\u00a0\u00a0Jaklitsch, Michael", "fencer_id": "81657", "club": "VASSAR", "rating": "A2016\u00a0", "rating_earned": "\u00a0"}, {"place": "11", "fencer_name": "\u00a0\u00a0Dolgonos, Mark", "fencer_id": "80518", "club": "NYFA", "rating": "A2017\u00a0", "rating_earned": "\u00a0"}, {"place": "12", "fencer_name": "\u00a0\u00a0Tableman, Douglas", "fencer_id": "54449", "club": "FC", "rating": "A2017\u00a0", "rating_earned": "\u00a0"}, {"place": "13", "fencer_name": "\u00a0\u00a0Wolf, Myles", "fencer_id": "44137", "club": "FC", "rating": "B2016\u00a0", "rating_earned": "\u00a0"}, {"place": "14", "fencer_name": "\u00a0\u00a0Levy, Kellen", "fencer_id": "132948", "club": "FAW", "rating": "D2018\u00a0", "rating_earned": "\u00a0"}, {"place": "15", "fencer_name": "\u00a0\u00a0Chaudhry, Rafay", "fencer_id": "121417", "club": "MORRIS FC", "rating": "C2017\u00a0", "rating_earned": "\u00a0"}, {"place": "16", "fencer_name": "\u00a0\u00a0Kang, Michael", "fencer_id": "107948", "club": "RFC", "rating": "B2018\u00a0", "rating_earned": "\u00a0"}, {"place": "17", "fencer_name": "\u00a0\u00a0Yi, Kyle", "fencer_id": "126107", "club": "UNAT", "rating": "A2018\u00a0", "rating_earned": "\u00a0"}, {"place": "18", "fencer_name": "\u00a0\u00a0Insler, Gabriel", "fencer_id": "65660", "club": "RIFAC", "rating": "B2018\u00a0", "rating_earned": "\u00a0"}, {"place": "19", "fencer_name": "\u00a0\u00a0Park, Minchan", "fencer_id": "125385", "club": "UNAT", "rating": "B2018\u00a0", "rating_earned": "\u00a0"}, {"place": "20", "fencer_name": "\u00a0\u00a0Chilana, Savitoz", "fencer_id": "85901", "club": "PHX", "rating": "B2017\u00a0", "rating_earned": "\u00a0"}, {"place": "21", "fencer_name": "\u00a0\u00a0Carvalho, Daniel", "fencer_id": "111890", "club": "CAMBRIDGE", "rating": "C2018\u00a0", "rating_earned": "\u00a0"}, {"place": "22", "fencer_name": "\u00a0\u00a0Dixon, Samuel", "fencer_id": "90007", "club": "FC", "rating": "D2017\u00a0", "rating_earned": "\u00a0"}, {"place": "23", "fencer_name": "\u00a0\u00a0Polkovsky, Dylan", "fencer_id": "100325", "club": "NYFA", "rating": "C2018\u00a0", "rating_earned": "\u00a0"}, {"place": "24", "fencer_name": "\u00a0\u00a0Cummings, Kai", "fencer_id": "113084", "club": "BOZEMAN", "rating": "C2017\u00a0", "rating_earned": "\u00a0"}, {"place": "25", "fencer_name": "\u00a0\u00a0Mogilevich, Michael", "fencer_id": "94996", "club": "NYFA", "rating": "B2016\u00a0", "rating_earned": "\u00a0"}, {"place": "26", "fencer_name": "\u00a0\u00a0Kumar, Anitya", "fencer_id": "115173", "club": "PRIHLSYMCA", "rating": "B2018\u00a0", "rating_earned": "\u00a0"}, {"place": "27", "fencer_name": "\u00a0\u00a0Lee, Woosuk", "fencer_id": "126099", "club": "FSA", "rating": "A2017\u00a0", "rating_earned": "\u00a0"}, {"place": "28", "fencer_name": "\u00a0\u00a0Kim, William", "fencer_id": "126097", "club": "RFC", "rating": "D2017\u00a0", "rating_earned": "\u00a0"}, {"place": "29", "fencer_name": "\u00a0\u00a0Kambeseles, Jack", "fencer_id": "97288", "club": "NYFA", "rating": "B2018\u00a0", "rating_earned": "\u00a0"}, {"place": "30", "fencer_name": "\u00a0\u00a0Benkler, Yuriy", "fencer_id": "113004", "club": "SL PALASZ", "rating": "B2018\u00a0", "rating_earned": "\u00a0"}, {"place": "31", "fencer_name": "\u00a0\u00a0Collado, Christopher", "fencer_id": "123966", "club": "MISSION FC", "rating": "C2016\u00a0", "rating_earned": "\u00a0"}, {"place": "32", "fencer_name": "\u00a0\u00a0Pavlenishvili, David", "fencer_id": "111818", "club": "FAW", "rating": "D2018\u00a0", "rating_earned": "\u00a0"}, {"place": "33", "fencer_name": "\u00a0\u00a0Gregory, Abram", "fencer_id": "71438", "club": "BVFA", "rating": "B2018\u00a0", "rating_earned": "\u00a0"}, {"place": "34", "fencer_name": "\u00a0\u00a0Shuster, Joshua", "fencer_id": "98036", "club": "NYFA", "rating": "B2017\u00a0", "rating_earned": "\u00a0"}, {"place": "34", "fencer_name": "\u00a0\u00a0Choi, Paul", "fencer_id": "51498", "club": "FC", "rating": "A2017\u00a0", "rating_earned": "\u00a0"}, {"place": "36", "fencer_name": "\u00a0\u00a0Wang, Jonathan", "fencer_id": "86590", "club": "AIF", "rating": "D2018\u00a0", "rating_earned": "\u00a0"}, {"place": "37", "fencer_name": "\u00a0\u00a0Zafft, Maximo", "fencer_id": "112915", "club": "MFA", "rating": "B2017\u00a0", "rating_earned": "\u00a0"}, {"place": "38", "fencer_name": "\u00a0\u00a0Park, Brian J", "fencer_id": "127589", "club": "RFC", "rating": "B2018\u00a0", "rating_earned": "\u00a0"}, {"place": "39", "fencer_name": "\u00a0\u00a0Mufel, Andrew", "fencer_id": "96102", "club": "NYFA", "rating": "B2017\u00a0", "rating_earned": "\u00a0"}, {"place": "40", "fencer_name": "\u00a0\u00a0Swerzenski, Daniel", "fencer_id": "71726", "club": "VASSAR", "rating": "A2016\u00a0", "rating_earned": "\u00a0"}, {"place": "41", "fencer_name": "\u00a0\u00a0Bekker, Mitchel", "fencer_id": "111863", "club": "NYFA", "rating": "E2017\u00a0", "rating_earned": "\u00a0"}, {"place": "42", "fencer_name": "\u00a0\u00a0Reyes, Vincent", "fencer_id": "129290", "club": "MISSION FC", "rating": "E2017\u00a0", "rating_earned": "\u00a0"}, {"place": "43", "fencer_name": "\u00a0\u00a0St. Onge, Alex", "fencer_id": "30984", "club": "H3", "rating": "B2018\u00a0", "rating_earned": "\u00a0"}, {"place": "44", "fencer_name": "\u00a0\u00a0O'Brien, Timothy S.", "fencer_id": "22788", "club": "UNAT", "rating": "U\u00a0", "rating_earned": "\u00a0"}, {"place": "45", "fencer_name": "\u00a0\u00a0Kravit, Connor BE", "fencer_id": "72275", "club": "FAW", "rating": "C2018\u00a0", "rating_earned": "\u00a0"}, {"place": "46", "fencer_name": "\u00a0\u00a0Hu, Matthew", "fencer_id": "125411", "club": "MISSION FC", "rating": "E2018\u00a0", "rating_earned": "\u00a0"}, {"place": "47", "fencer_name": "\u00a0\u00a0Shine, Peter", "fencer_id": "107847", "club": "RFC", "rating": "D2018\u00a0", "rating_earned": "\u00a0"}, {"place": "48", "fencer_name": "\u00a0\u00a0Gibson, Nowell", "fencer_id": "91238", "club": "FAW", "rating": "C2017\u00a0", "rating_earned": "\u00a0"}, {"place": "49", "fencer_name": "\u00a0\u00a0Levy, Jeff", "fencer_id": "143853", "club": "FAW", "rating": "E2018\u00a0", "rating_earned": "\u00a0"}, {"place": "50", "fencer_name": "\u00a0\u00a0Lehr, Will", "fencer_id": "125413", "club": "MISSION FC", "rating": "D2018\u00a0", "rating_earned": "\u00a0"}, {"place": "51", "fencer_name": "\u00a0\u00a0Wisniewski, Bart", "fencer_id": "151521", "club": "H3", "rating": "U\u00a0", "rating_earned": "\u00a0"}, {"place": "52", "fencer_name": "\u00a0\u00a0Li, Brian", "fencer_id": "145118", "club": "ISLAND NY", "rating": "U\u00a0", "rating_earned": "\u00a0"}, {"place": "53", "fencer_name": "\u00a0\u00a0Singh Rana, Shamtej", "fencer_id": "154431", "club": "MISSION FC", "rating": "U\u00a0", "rating_earned": "\u00a0"}]}, {"event_name": ["\n", "C & Under Senior Men's Epee:\u00a0\u00a0\u00a0\n19 Competitors, a D1 Event\n\u00a0\u00a0\u00a0\u00a0\u00a0\u00a0\n", "\n"], "event_id": "159027", "fencers": [{"place": "1", "fencer_name": "\u00a0\u00a0Gibson, Nowell", "fencer_id": "91238", "club": "FAW", "rating": "C2017\u00a0", "rating_earned": "\u00a0"}, {"place": "2", "fencer_name": "\u00a0\u00a0Marchant, Albert", "fencer_id": "114474", "club": "PFC", "rating": "D2018\u00a0", "rating_earned": "\u00a0"}, {"place": "3", "fencer_name": "\u00a0\u00a0Levy, Kellen", "fencer_id": "132948", "club": "FAW", "rating": "D2018\u00a0", "rating_earned": "\u00a0"}, {"place": "3", "fencer_name": "\u00a0\u00a0Wang, Jonathan", "fencer_id": "86590", "club": "AIF", "rating": "D2018\u00a0", "rating_earned": "\u00a0"}, {"place": "5", "fencer_name": "\u00a0\u00a0Spano, Gideon", "fencer_id": "83278", "club": "RFC", "rating": "E2017\u00a0", "rating_earned": "\u00a0"}, {"place": "6", "fencer_name": "\u00a0\u00a0Pavlenishvili, David", "fencer_id": "111818", "club": "FAW", "rating": "D2018\u00a0", "rating_earned": "\u00a0"}, {"place": "7", "fencer_name": "\u00a0\u00a0Shine, Peter", "fencer_id": "107847", "club": "RFC", "rating": "D2018\u00a0", "rating_earned": "\u00a0"}, {"place": "8", "fencer_name": "\u00a0\u00a0Levy, Jeff", "fencer_id": "143853", "club": "FAW", "rating": "E2018\u00a0", "rating_earned": "\u00a0"}, {"place": "9", "fencer_name": "\u00a0\u00a0Cummings, Kai", "fencer_id": "113084", "club": "BOZEMAN", "rating": "C2017\u00a0", "rating_earned": "\u00a0"}, {"place": "10", "fencer_name": "\u00a0\u00a0Cruz, Cyrus", "fencer_id": "146417", "club": "WESTBROOK", "rating": "U\u00a0", "rating_earned": "\u00a0"}, {"place": "11", "fencer_name": "\u00a0\u00a0Shi, Paul", "fencer_id": "156294", "club": "UNAT", "rating": "U\u00a0", "rating_earned": "\u00a0"}, {"place": "12", "fencer_name": "\u00a0\u00a0Wisniewski, Bart", "fencer_id": "151521", "club": "H3", "rating": "U\u00a0", "rating_earned": "\u00a0"}, {"place": "13", "fencer_name": "\u00a0\u00a0Lehr, Will", "fencer_id": "125413", "club": "MISSION FC", "rating": "D2018\u00a0", "rating_earned": "\u00a0"}, {"place": "14", "fencer_name": "\u00a0\u00a0Reyes, Vincent", "fencer_id": "129290", "club": "MISSION FC", "rating": "E2017\u00a0", "rating_earned": "\u00a0"}, {"place": "15", "fencer_name": "\u00a0\u00a0Li, Brian", "fencer_id": "145118", "club": "ISLAND NY", "rating": "U\u00a0", "rating_earned": "\u00a0"}, {"place": "16", "fencer_name": "\u00a0\u00a0Fenwick, Luke", "fencer_id": "72904", "club": "PFC", "rating": "D2018\u00a0", "rating_earned": "\u00a0"}, {"place": "17", "fencer_name": "\u00a0\u00a0O'Brien, Timothy S.", "fencer_id": "22788", "club": "UNAT", "rating": "U\u00a0", "rating_earned": "\u00a0"}, {"place": "18", "fencer_name": "\u00a0\u00a0Parte, Aidan", "fencer_id": "141559", "club": "MFA", "rating": "D2018\u00a0", "rating_earned": "\u00a0"}, {"place": "19", "fencer_name": "\u00a0\u00a0Singh Rana, Shamtej", "fencer_id": "154431", "club": "MISSION FC", "rating": "U\u00a0", "rating_earned": "\u00a0"}]}, {"event_name": ["\n", "Div 1A Senior Men's Foil:\u00a0\u00a0\u00a0\n81 Competitors, a A4 Event\n\u00a0\u00a0\u00a0\u00a0\u00a0\u00a0\n", "\n"], "event_id": "159028", "fencers": [{"place": "1", "fencer_name": "\u00a0\u00a0Li, Brian", "fencer_id": "75355", "club": "MFA", "rating": "A2017\u00a0", "rating_earned": "A2018\u00a0"}, {"place": "2", "fencer_name": "\u00a0\u00a0Zhang, Daniel", "fencer_id": "92809", "club": "OLYMPIAFC", "rating": "B2018\u00a0", "rating_earned": "A2018\u00a0"}, {"place": "3", "fencer_name": "\u00a0\u00a0Holmes, Andrew", "fencer_id": "35845", "club": "MISSION FC", "rating": "A2017\u00a0", "rating_earned": "A2018\u00a0"}, {"place": "3", "fencer_name": "\u00a0\u00a0Holmes, Stuart", "fencer_id": "36943", "club": "MISSION FC", "rating": "A2017\u00a0", "rating_earned": "A2018\u00a0"}, {"place": "5", "fencer_name": "\u00a0\u00a0Andrade, Nicholas", "fencer_id": "55623", "club": "MOE FC", "rating": "A2018\u00a0", "rating_earned": "\u00a0"}, {"place": "6", "fencer_name": "\u00a0\u00a0Gruber, Samuel", "fencer_id": "47170", "club": "MOE FC", "rating": "A2017\u00a0", "rating_earned": "A2018\u00a0"}, {"place": "7", "fencer_name": "\u00a0\u00a0Emmer, Chase", "fencer_id": "82375", "club": "VFC", "rating": "A2018\u00a0", "rating_earned": "\u00a0"}, {"place": "8", "fencer_name": "\u00a0\u00a0Hodges, Carter", "fencer_id": "67702", "club": "MANHATTAN", "rating": "A2018\u00a0", "rating_earned": "\u00a0"}, {"place": "9", "fencer_name": "\u00a0\u00a0Welch, Kyle", "fencer_id": "90088", "club": "UNAT", "rating": "A2017\u00a0", "rating_earned": "\u00a0"}, {"place": "10", "fencer_name": "\u00a0\u00a0Hempe, Jake", "fencer_id": "106952", "club": "MISSION FC", "rating": "B2017\u00a0", "rating_earned": "B2018\u00a0"}, {"place": "11", "fencer_name": "\u00a0\u00a0Wetmore, Lucas", "fencer_id": "73480", "club": "UNAT", "rating": "B2017\u00a0", "rating_earned": "B2018\u00a0"}, {"place": "12", "fencer_name": "\u00a0\u00a0Lutar, Lucas", "fencer_id": "91806", "club": "FAW", "rating": "A2017\u00a0", "rating_earned": "\u00a0"}, {"place": "13", "fencer_name": "\u00a0\u00a0Peter, Griffin", "fencer_id": "91629", "club": "RFC", "rating": "C2018\u00a0", "rating_earned": "B2018\u00a0"}, {"place": "14", "fencer_name": "\u00a0\u00a0Liu, Patrick", "fencer_id": "67510", "club": "IFABOSTON", "rating": "A2017\u00a0", "rating_earned": "\u00a0"}, {"place": "15", "fencer_name": "\u00a0\u00a0Gilbert-Goldstein, Avery", "fencer_id": "97878", "club": "BBFC", "rating": "C2018\u00a0", "rating_earned": "B2018\u00a0"}, {"place": "16", "fencer_name": "\u00a0\u00a0Liu, Niles", "fencer_id": "89155", "club": "IFABOSTON", "rating": "B2017\u00a0", "rating_earned": "B2018\u00a0"}, {"place": "17", "fencer_name": "\u00a0\u00a0Gee, Brandon", "fencer_id": "131833", "club": "GUTKOVSKIY", "rating": "B2018\u00a0", "rating_earned": "\u00a0"}, {"place": "18", "fencer_name": "\u00a0\u00a0Cheng, Thomas", "fencer_id": "104120", "club": "MOE FC", "rating": "B2018\u00a0", "rating_earned": "\u00a0"}, {"place": "19", "fencer_name": "\u00a0\u00a0Blutt, Emerson", "fencer_id": "84020", "club": "MANHATTAN", "rating": "B2018\u00a0", "rating_earned": "\u00a0"}, {"place": "20", "fencer_name": "\u00a0\u00a0Brandt-Ogman, Adlai", "fencer_id": "29527", "club": "VASSAR", "rating": "C2017\u00a0", "rating_earned": "C2018\u00a0"}, {"place": "21", "fencer_name": "\u00a0\u00a0Prince, Nicholas", "fencer_id": "110962", "club": "BBFC", "rating": "B2017\u00a0", "rating_earned": "\u00a0"}, {"place": "22", "fencer_name": "\u00a0\u00a0Acinapuro, Philip", "fencer_id": "124438", "club": "5T FC", "rating": "B2017\u00a0", "rating_earned": "\u00a0"}, {"place": "23", "fencer_name": "\u00a0\u00a0Oursler, Jack", "fencer_id": "84692", "club": "MANHATTAN", "rating": "A2018\u00a0", "rating_earned": "\u00a0"}, {"place": "24", "fencer_name": "\u00a0\u00a0Dobbins, Evan", "fencer_id": "25030", "club": "FSC", "rating": "B2017\u00a0", "rating_earned": "\u00a0"}, {"place": "25", "fencer_name": "\u00a0\u00a0Ding, Jonathan", "fencer_id": "104945", "club": "MFA", "rating": "B2017\u00a0", "rating_earned": "\u00a0"}, {"place": "26", "fencer_name": "\u00a0\u00a0Liu, Eric", "fencer_id": "118721", "club": "VFC", "rating": "C2018\u00a0", "rating_earned": "\u00a0"}, {"place": "27", "fencer_name": "\u00a0\u00a0Taqi, Ahmad", "fencer_id": "137825", "club": "UNAT", "rating": "A2017\u00a0", "rating_earned": "\u00a0"}, {"place": "28", "fencer_name": "\u00a0\u00a0Li, Brandon", "fencer_id": "81870", "club": "MFA", "rating": "B2017\u00a0", "rating_earned": "\u00a0"}, {"place": "29", "fencer_name": "\u00a0\u00a0Yang, Adam", "fencer_id": "72728", "club": "OLYMPIAFC", "rating": "B2017\u00a0", "rating_earned": "\u00a0"}, {"place": "30", "fencer_name": "\u00a0\u00a0Chen, Lei", "fencer_id": "107094", "club": "IFABOSTON", "rating": "B2017\u00a0", "rating_earned": "\u00a0"}, {"place": "31", "fencer_name": "\u00a0\u00a0Stanley, Mason", "fencer_id": "128957", "club": "RICHMD FC", "rating": "C2018\u00a0", "rating_earned": "\u00a0"}, {"place": "32", "fencer_name": "\u00a0\u00a0Marshall, Ian", "fencer_id": "116221", "club": "RIFAC", "rating": "D2018\u00a0", "rating_earned": "\u00a0"}, {"place": "33", "fencer_name": "\u00a0\u00a0Litle, Elishua", "fencer_id": "115260", "club": "MOE FC", "rating": "A2017\u00a0", "rating_earned": "\u00a0"}, {"place": "34", "fencer_name": "\u00a0\u00a0Hu, Oliver", "fencer_id": "92812", "club": "MFA", "rating": "B2017\u00a0", "rating_earned": "\u00a0"}, {"place": "35", "fencer_name": "\u00a0\u00a0Healy, Griffen", "fencer_id": "63127", "club": "NSFC", "rating": "C2017\u00a0", "rating_earned": "\u00a0"}, {"place": "36", "fencer_name": "\u00a0\u00a0Liu, Jonathan", "fencer_id": "98855", "club": "BOSTON FC", "rating": "B2018\u00a0", "rating_earned": "\u00a0"}, {"place": "37", "fencer_name": "\u00a0\u00a0Jang, Jaewon", "fencer_id": "136357", "club": "TOP FC", "rating": "A2017\u00a0", "rating_earned": "\u00a0"}, {"place": "38", "fencer_name": "\u00a0\u00a0Riccio, Frank", "fencer_id": "92421", "club": "FAIRFIELD", "rating": "B2017\u00a0", "rating_earned": "\u00a0"}, {"place": "39", "fencer_name": "\u00a0\u00a0Grossman Smisek, Spencer", "fencer_id": "95268", "club": "FC", "rating": "D2017\u00a0", "rating_earned": "\u00a0"}, {"place": "40", "fencer_name": "\u00a0\u00a0Siegel, Elliot", "fencer_id": "113413", "club": "CANDLEWOOD", "rating": "C2017\u00a0", "rating_earned": "\u00a0"}, {"place": "41", "fencer_name": "\u00a0\u00a0Andrews, Nathan", "fencer_id": "108790", "club": "FAW", "rating": "B2018\u00a0", "rating_earned": "\u00a0"}, {"place": "42", "fencer_name": "\u00a0\u00a0Ancona, Christopher", "fencer_id": "107486", "club": "MISSION FC", "rating": "E2017\u00a0", "rating_earned": "E2018\u00a0"}, {"place": "43", "fencer_name": "\u00a0\u00a0Ma, Alexander", "fencer_id": "77012", "club": "MFA", "rating": "C2018\u00a0", "rating_earned": "\u00a0"}, {"place": "44", "fencer_name": "\u00a0\u00a0Israelian, Marat", "fencer_id": "46883", "club": "FC", "rating": "U\u00a0", "rating_earned": "E2018\u00a0"}, {"place": "45", "fencer_name": "\u00a0\u00a0Spirli, Francesco", "fencer_id": "103247", "club": "SCFC", "rating": "B2017\u00a0", "rating_earned": "\u00a0"}, {"place": "46", "fencer_name": "\u00a0\u00a0Schenck, Koen", "fencer_id": "128357", "club": "RIFAC", "rating": "E2018\u00a0", "rating_earned": "\u00a0"}, {"place": "47", "fencer_name": "\u00a0\u00a0Lin, Richard", "fencer_id": "124690", "club": "FAW", "rating": "C2018\u00a0", "rating_earned": "\u00a0"}, {"place": "47", "fencer_name": "\u00a0\u00a0Reals, Alden", "fencer_id": "78001", "club": "FC", "rating": "E2018\u00a0", "rating_earned": "\u00a0"}, {"place": "49", "fencer_name": "\u00a0\u00a0Augustine, Ethan", "fencer_id": "122488", "club": "GUTKOVSKIY", "rating": "C2018\u00a0", "rating_earned": "\u00a0"}, {"place": "50", "fencer_name": "\u00a0\u00a0Wu, Albert", "fencer_id": "108627", "club": "MFA", "rating": "A2017\u00a0", "rating_earned": "\u00a0"}, {"place": "51", "fencer_name": "\u00a0\u00a0Sullivan, Jackson", "fencer_id": "73125", "club": "MOE FC", "rating": "D2018\u00a0", "rating_earned": "\u00a0"}, {"place": "52", "fencer_name": "\u00a0\u00a0Desando, Michael", "fencer_id": "119580", "club": "MISSION FC", "rating": "D2018\u00a0", "rating_earned": "\u00a0"}, {"place": "53", "fencer_name": "\u00a0\u00a0Lee, Daniel", "fencer_id": "144532", "club": "5T FC", "rating": "D2018\u00a0", "rating_earned": "\u00a0"}, {"place": "54", "fencer_name": "\u00a0\u00a0Yu, Vinni", "fencer_id": "107829", "club": "TOP FC", "rating": "D2017\u00a0", "rating_earned": "\u00a0"}, {"place": "55", "fencer_name": "\u00a0\u00a0Sylvester, William", "fencer_id": "129542", "club": "VIRGNIA AF", "rating": "E2018\u00a0", "rating_earned": "\u00a0"}, {"place": "56", "fencer_name": "\u00a0\u00a0Artis, Tre", "fencer_id": "80596", "club": "BOSTON FC", "rating": "C2016\u00a0", "rating_earned": "\u00a0"}, {"place": "57", "fencer_name": "\u00a0\u00a0Cortizas, Jack", "fencer_id": "45972", "club": "BOSTON FC", "rating": "C2017\u00a0", "rating_earned": "\u00a0"}, {"place": "58", "fencer_name": "\u00a0\u00a0Liu, Kevin", "fencer_id": "115522", "club": "OLYMPIAFC", "rating": "C2018\u00a0", "rating_earned": "\u00a0"}, {"place": "59", "fencer_name": "\u00a0\u00a0Batrak, Alexander", "fencer_id": "104970", "club": "CANDLEWOOD", "rating": "B2017\u00a0", "rating_earned": "\u00a0"}, {"place": "60", "fencer_name": "\u00a0\u00a0Cook, John", "fencer_id": "122328", "club": "BBFC", "rating": "C2018\u00a0", "rating_earned": "\u00a0"}, {"place": "61", "fencer_name": "\u00a0\u00a0Cho, Justin", "fencer_id": "126026", "club": "PREMIER FC", "rating": "B2016\u00a0", "rating_earned": "\u00a0"}, {"place": "62", "fencer_name": "\u00a0\u00a0Zhou, Timmy", "fencer_id": "105340", "club": "RIFAC", "rating": "C2018\u00a0", "rating_earned": "\u00a0"}, {"place": "63", "fencer_name": "\u00a0\u00a0St. Clair, Regan", "fencer_id": "119334", "club": "MISSION FC", "rating": "D2018\u00a0", "rating_earned": "\u00a0"}, {"place": "64", "fencer_name": "\u00a0\u00a0Healy, Tyler", "fencer_id": "14675", "club": "5T FC", "rating": "D2017\u00a0", "rating_earned": "\u00a0"}, {"place": "65", "fencer_name": "\u00a0\u00a0Chan, Tyler", "fencer_id": "93127", "club": "UNAT", "rating": "E2018\u00a0", "rating_earned": "\u00a0"}, {"place": "66", "fencer_name": "\u00a0\u00a0Baumstein, Nicholas", "fencer_id": "110106", "club": "BBFC", "rating": "C2018\u00a0", "rating_earned": "\u00a0"}, {"place": "66", "fencer_name": "\u00a0\u00a0Park, Joah", "fencer_id": "73614", "club": "NYU", "rating": "C2017\u00a0", "rating_earned": "\u00a0"}, {"place": "68", "fencer_name": "\u00a0\u00a0Craley, Thomas", "fencer_id": "83452", "club": "CANDLEWOOD", "rating": "C2017\u00a0", "rating_earned": "\u00a0"}, {"place": "69", "fencer_name": "\u00a0\u00a0Maurer, Ned", "fencer_id": "51827", "club": "RICHMD FC", "rating": "C2018\u00a0", "rating_earned": "\u00a0"}, {"place": "70", "fencer_name": "\u00a0\u00a0Badrigian, William", "fencer_id": "73029", "club": "SCFC", "rating": "B2018\u00a0", "rating_earned": "\u00a0"}, {"place": "71", "fencer_name": "\u00a0\u00a0Park, Noah", "fencer_id": "73615", "club": "GUTKOVSKIY", "rating": "B2016\u00a0", "rating_earned": "\u00a0"}, {"place": "72", "fencer_name": "\u00a0\u00a0Goguen-Compagnoni, Nicholas", "fencer_id": "125244", "club": "NJFA", "rating": "D2017\u00a0", "rating_earned": "\u00a0"}, {"place": "73", "fencer_name": "\u00a0\u00a0Klein, Caleb", "fencer_id": "70115", "club": "FAW", "rating": "C2016\u00a0", "rating_earned": "\u00a0"}, {"place": "74", "fencer_name": "\u00a0\u00a0Hu, Robin", "fencer_id": "149838", "club": "VFC", "rating": "U\u00a0", "rating_earned": "\u00a0"}, {"place": "75", "fencer_name": "\u00a0\u00a0Schkoda, Jeremy", "fencer_id": "126521", "club": "MISSION FC", "rating": "U\u00a0", "rating_earned": "\u00a0"}, {"place": "76", "fencer_name": "\u00a0\u00a0Fedonchik, Henry", "fencer_id": "84129", "club": "MANHATTAN", "rating": "U\u00a0", "rating_earned": "\u00a0"}, {"place": "77", "fencer_name": "\u00a0\u00a0Galler, Dave", "fencer_id": "29164", "club": "MISSION FC", "rating": "U\u00a0", "rating_earned": "\u00a0"}, {"place": "78", "fencer_name": "\u00a0\u00a0Yu, Dale", "fencer_id": "125414", "club": "MISSION FC", "rating": "U\u00a0", "rating_earned": "\u00a0"}, {"place": "79", "fencer_name": "\u00a0\u00a0Dyckman, Andrew", "fencer_id": "131521", "club": "MISSION FC", "rating": "E2018\u00a0", "rating_earned": "\u00a0"}, {"place": "79", "fencer_name": "\u00a0\u00a0Montalbine, Aidan", "fencer_id": "129603", "club": "MISSION FC", "rating": "U\u00a0", "rating_earned": "\u00a0"}, {"place": "81", "fencer_name": "\u00a0\u00a0Cutolo, Connor", "fencer_id": "132074", "club": "MISSION FC", "rating": "U\u00a0", "rating_earned": "\u00a0"}]}, {"event_name": ["\n", "C & Under Senior Men's Foil:\u00a0\u00a0\u00a0\n40 Competitors, a C2 Event\n\u00a0\u00a0\u00a0\u00a0\u00a0\u00a0\n", "\n"], "event_id": "159029", "fencers": [{"place": "1", "fencer_name": "\u00a0\u00a0Peter, Griffin", "fencer_id": "91629", "club": "RFC", "rating": "C2018\u00a0", "rating_earned": "\u00a0"}, {"place": "2", "fencer_name": "\u00a0\u00a0Stanley, Mason", "fencer_id": "128957", "club": "RICHMD FC", "rating": "C2018\u00a0", "rating_earned": "\u00a0"}, {"place": "3", "fencer_name": "\u00a0\u00a0Ho, Ryan", "fencer_id": "109601", "club": "VFC", "rating": "C2018\u00a0", "rating_earned": "\u00a0"}, {"place": "3", "fencer_name": "\u00a0\u00a0Healy, Griffen", "fencer_id": "63127", "club": "NSFC", "rating": "C2017\u00a0", "rating_earned": "\u00a0"}, {"place": "5", "fencer_name": "\u00a0\u00a0Desando, Michael", "fencer_id": "119580", "club": "MISSION FC", "rating": "D2018\u00a0", "rating_earned": "\u00a0"}, {"place": "6", "fencer_name": "\u00a0\u00a0Lin, Richard", "fencer_id": "124690", "club": "FAW", "rating": "C2018\u00a0", "rating_earned": "\u00a0"}, {"place": "7", "fencer_name": "\u00a0\u00a0Klein, Caleb", "fencer_id": "70115", "club": "FAW", "rating": "C2016\u00a0", "rating_earned": "\u00a0"}, {"place": "8", "fencer_name": "\u00a0\u00a0Artis, Tre", "fencer_id": "80596", "club": "BOSTON FC", "rating": "C2016\u00a0", "rating_earned": "\u00a0"}, {"place": "9", "fencer_name": "\u00a0\u00a0Lee, Daniel", "fencer_id": "144532", "club": "5T FC", "rating": "D2018\u00a0", "rating_earned": "\u00a0"}, {"place": "10", "fencer_name": "\u00a0\u00a0Maurer, Ned", "fencer_id": "51827", "club": "RICHMD FC", "rating": "C2018\u00a0", "rating_earned": "\u00a0"}, {"place": "11", "fencer_name": "\u00a0\u00a0St. Clair, Regan", "fencer_id": "119334", "club": "MISSION FC", "rating": "D2018\u00a0", "rating_earned": "\u00a0"}, {"place": "12", "fencer_name": "\u00a0\u00a0Reals, Alden", "fencer_id": "78001", "club": "FC", "rating": "E2018\u00a0", "rating_earned": "\u00a0"}, {"place": "13", "fencer_name": "\u00a0\u00a0Marshall, Ian", "fencer_id": "116221", "club": "RIFAC", "rating": "D2018\u00a0", "rating_earned": "\u00a0"}, {"place": "14", "fencer_name": "\u00a0\u00a0Cortizas, Jack", "fencer_id": "45972", "club": "BOSTON FC", "rating": "C2017\u00a0", "rating_earned": "\u00a0"}, {"place": "15", "fencer_name": "\u00a0\u00a0Ancona, Christopher", "fencer_id": "107486", "club": "MISSION FC", "rating": "E2017\u00a0", "rating_earned": "\u00a0"}, {"place": "16", "fencer_name": "\u00a0\u00a0Advincula, Dashiell", "fencer_id": "140847", "club": "BBFC", "rating": "E2018\u00a0", "rating_earned": "\u00a0"}, {"place": "17", "fencer_name": "\u00a0\u00a0Chan, Tyler", "fencer_id": "93127", "club": "UNAT", "rating": "E2018\u00a0", "rating_earned": "\u00a0"}, {"place": "18", "fencer_name": "\u00a0\u00a0Sylvester, William", "fencer_id": "129542", "club": "VIRGNIA AF", "rating": "E2018\u00a0", "rating_earned": "\u00a0"}, {"place": "19", "fencer_name": "\u00a0\u00a0Insler, Ethan", "fencer_id": "81496", "club": "RIFAC", "rating": "E2018\u00a0", "rating_earned": "\u00a0"}, {"place": "20", "fencer_name": "\u00a0\u00a0Schenck, Koen", "fencer_id": "128357", "club": "RIFAC", "rating": "E2018\u00a0", "rating_earned": "\u00a0"}, {"place": "21", "fencer_name": "\u00a0\u00a0Soumakis, Sarantos", "fencer_id": "127003", "club": "UNAT", "rating": "D2017\u00a0", "rating_earned": "\u00a0"}, {"place": "22", "fencer_name": "\u00a0\u00a0Tsai, Philip", "fencer_id": "107653", "club": "MOE FC", "rating": "D2017\u00a0", "rating_earned": "\u00a0"}, {"place": "23", "fencer_name": "\u00a0\u00a0Dyckman, Andrew", "fencer_id": "131521", "club": "MISSION FC", "rating": "E2018\u00a0", "rating_earned": "\u00a0"}, {"place": "24", "fencer_name": "\u00a0\u00a0Pandya, Poojan", "fencer_id": "129610", "club": "H3", "rating": "U\u00a0", "rating_earned": "\u00a0"}, {"place": "25", "fencer_name": "\u00a0\u00a0Bova, Andrew", "fencer_id": "119551", "club": "MISSION FC", "rating": "U\u00a0", "rating_earned": "\u00a0"}, {"place": "25", "fencer_name": "\u00a0\u00a0Lee, Joon", "fencer_id": "144728", "club": "H3", "rating": "U\u00a0", "rating_earned": "\u00a0"}, {"place": "27", "fencer_name": "\u00a0\u00a0Sheikh, Arham", "fencer_id": "144741", "club": "H3", "rating": "U\u00a0", "rating_earned": "\u00a0"}, {"place": "28", "fencer_name": "\u00a0\u00a0Amodemo, Charles", "fencer_id": "126656", "club": "MISSION FC", "rating": "U\u00a0", "rating_earned": "\u00a0"}, {"place": "29", "fencer_name": "\u00a0\u00a0Meyers, Lee", "fencer_id": "130208", "club": "DURKAN FA", "rating": "E2017\u00a0", "rating_earned": "\u00a0"}, {"place": "30", "fencer_name": "\u00a0\u00a0Weinkopf, William", "fencer_id": "108233", "club": "RIFAC", "rating": "D2018\u00a0", "rating_earned": "\u00a0"}, {"place": "31", "fencer_name": "\u00a0\u00a0Yu, Dale", "fencer_id": "125414", "club": "MISSION FC", "rating": "U\u00a0", "rating_earned": "\u00a0"}, {"place": "32", "fencer_name": "\u00a0\u00a0Miller, Andrew", "fencer_id": "151755", "club": "SCFC", "rating": "U\u00a0", "rating_earned": "\u00a0"}, {"place": "33", "fencer_name": "\u00a0\u00a0Galler, Dave", "fencer_id": "29164", "club": "MISSION FC", "rating": "U\u00a0", "rating_earned": "\u00a0"}, {"place": "34", "fencer_name": "\u00a0\u00a0Schkoda, Jeremy", "fencer_id": "126521", "club": "MISSION FC", "rating": "U\u00a0", "rating_earned": "\u00a0"}, {"place": "35", "fencer_name": "\u00a0\u00a0Durkee, Porter", "fencer_id": "150466", "club": "PCFC", "rating": "U\u00a0", "rating_earned": "\u00a0"}, {"place": "36", "fencer_name": "\u00a0\u00a0Montalbine, Aidan", "fencer_id": "129603", "club": "MISSION FC", "rating": "U\u00a0", "rating_earned": "\u00a0"}, {"place": "37", "fencer_name": "\u00a0\u00a0Zhao, Jesse", "fencer_id": "132736", "club": "IFABOSTON", "rating": "E2017\u00a0", "rating_earned": "\u00a0"}, {"place": "38", "fencer_name": "\u00a0\u00a0Grassie, James", "fencer_id": "152952", "club": "UNAT", "rating": "U\u00a0", "rating_earned": "\u00a0"}, {"place": "39", "fencer_name": "\u00a0\u00a0Cutolo, Connor", "fencer_id": "132074", "club": "MISSION FC", "rating": "U\u00a0", "rating_earned": "\u00a0"}, {"place": "40", "fencer_name": "\u00a0\u00a0Chen, Zihao", "fencer_id": "150180", "club": "MFA", "rating": "U\u00a0", "rating_earned": "\u00a0"}]}, {"event_name": ["\n", "Div 1A Senior Men's Saber:\u00a0\u00a0\u00a0\n35 Competitors, a B2 Event\n\u00a0\u00a0\u00a0\u00a0\u00a0\u00a0\n", "\n"], "event_id": "159030", "fencers": [{"place": "1", "fencer_name": "\u00a0\u00a0Lee, Ivan", "fencer_id": "32765", "club": "WESTBROOK", "rating": "A2016\u00a0", "rating_earned": "\u00a0"}, {"place": "2", "fencer_name": "\u00a0\u00a0Descherer, David", "fencer_id": "95075", "club": "BERGEN FC", "rating": "B2017\u00a0", "rating_earned": "\u00a0"}, {"place": "3", "fencer_name": "\u00a0\u00a0Lin, John", "fencer_id": "98951", "club": "SFC", "rating": "B2018\u00a0", "rating_earned": "\u00a0"}, {"place": "3", "fencer_name": "\u00a0\u00a0Yen, Darren", "fencer_id": "111321", "club": "INTEGRITY", "rating": "B2018\u00a0", "rating_earned": "\u00a0"}, {"place": "5", "fencer_name": "\u00a0\u00a0Dammer, Mark", "fencer_id": "139168", "club": "H3", "rating": "C2017\u00a0", "rating_earned": "\u00a0"}, {"place": "6", "fencer_name": "\u00a0\u00a0Silversmith, Zachary", "fencer_id": "30975", "club": "NYAC", "rating": "C2016\u00a0", "rating_earned": "\u00a0"}, {"place": "7", "fencer_name": "\u00a0\u00a0Golia, Michael", "fencer_id": "37180", "club": "NYAC", "rating": "C2015\u00a0", "rating_earned": "\u00a0"}, {"place": "8", "fencer_name": "\u00a0\u00a0Laks, Matthew", "fencer_id": "55005", "club": "NYAC", "rating": "D2016\u00a0", "rating_earned": "D2018\u00a0"}, {"place": "9", "fencer_name": "\u00a0\u00a0Moskowitz, Mason", "fencer_id": "105409", "club": "KSA", "rating": "E2018\u00a0", "rating_earned": "\u00a0"}, {"place": "10", "fencer_name": "\u00a0\u00a0Han, Nicholas", "fencer_id": "91102", "club": "BERGEN FC", "rating": "B2017\u00a0", "rating_earned": "\u00a0"}, {"place": "11", "fencer_name": "\u00a0\u00a0Tang, Brian", "fencer_id": "89361", "club": "ESCRIMEUR", "rating": "E2018\u00a0", "rating_earned": "\u00a0"}, {"place": "11", "fencer_name": "\u00a0\u00a0Michell, Bailey", "fencer_id": "65661", "club": "IFC", "rating": "C2017\u00a0", "rating_earned": "\u00a0"}, {"place": "13", "fencer_name": "\u00a0\u00a0Harris, Alex", "fencer_id": "111870", "club": "SHERIDAN", "rating": "E2018\u00a0", "rating_earned": "\u00a0"}, {"place": "14", "fencer_name": "\u00a0\u00a0Wu, Nicholas", "fencer_id": "121709", "club": "MANHATTAN", "rating": "C2017\u00a0", "rating_earned": "\u00a0"}, {"place": "14", "fencer_name": "\u00a0\u00a0Offutt, Tyler", "fencer_id": "87766", "club": "MISSION FC", "rating": "D2018\u00a0", "rating_earned": "\u00a0"}, {"place": "16", "fencer_name": "\u00a0\u00a0Bartolo, Domenic", "fencer_id": "119581", "club": "MISSION FC", "rating": "D2018\u00a0", "rating_earned": "\u00a0"}, {"place": "17", "fencer_name": "\u00a0\u00a0Travaglione, Conor", "fencer_id": "136427", "club": "H3", "rating": "C2018\u00a0", "rating_earned": "\u00a0"}, {"place": "18", "fencer_name": "\u00a0\u00a0Greenbaum, Maxwell", "fencer_id": "91623", "club": "NELLYA", "rating": "B2017\u00a0", "rating_earned": "\u00a0"}, {"place": "19", "fencer_name": "\u00a0\u00a0Tian, Albert", "fencer_id": "144298", "club": "MISSION FC", "rating": "D2018\u00a0", "rating_earned": "\u00a0"}, {"place": "20", "fencer_name": "\u00a0\u00a0Takemaru, Leo", "fencer_id": "125574", "club": "MISSION FC", "rating": "E2018\u00a0", "rating_earned": "\u00a0"}, {"place": "21", "fencer_name": "\u00a0\u00a0Hennicke, Michael", "fencer_id": "114987", "club": "ATLANTIC", "rating": "D2017\u00a0", "rating_earned": "\u00a0"}, {"place": "22", "fencer_name": "\u00a0\u00a0Epstein, Henry", "fencer_id": "111360", "club": "INTEGRITY", "rating": "E2017\u00a0", "rating_earned": "\u00a0"}, {"place": "23", "fencer_name": "\u00a0\u00a0Hong, Marshall", "fencer_id": "130760", "club": "BERGEN FC", "rating": "D2018\u00a0", "rating_earned": "\u00a0"}, {"place": "24", "fencer_name": "\u00a0\u00a0Yen, Preston", "fencer_id": "128347", "club": "INTEGRITY", "rating": "D2018\u00a0", "rating_earned": "\u00a0"}, {"place": "25", "fencer_name": "\u00a0\u00a0Deto, Daniel", "fencer_id": "87266", "club": "MISSION FC", "rating": "C2016\u00a0", "rating_earned": "\u00a0"}, {"place": "26", "fencer_name": "\u00a0\u00a0Wolin, Zachary", "fencer_id": "44703", "club": "TIM MOREHO", "rating": "D2018\u00a0", "rating_earned": "\u00a0"}, {"place": "27", "fencer_name": "\u00a0\u00a0Guzman, R J", "fencer_id": "77767", "club": "INTEGRITY", "rating": "C2017\u00a0", "rating_earned": "\u00a0"}, {"place": "28", "fencer_name": "\u00a0\u00a0Morris, Samuel", "fencer_id": "138298", "club": "H3", "rating": "E2017\u00a0", "rating_earned": "\u00a0"}, {"place": "29", "fencer_name": "\u00a0\u00a0Dunn, Jack", "fencer_id": "106945", "club": "MISSION FC", "rating": "U\u00a0", "rating_earned": "\u00a0"}, {"place": "30", "fencer_name": "\u00a0\u00a0Liu, Kelly", "fencer_id": "147495", "club": "MISSION FC", "rating": "U\u00a0", "rating_earned": "\u00a0"}, {"place": "31", "fencer_name": "\u00a0\u00a0Mudgal, Arjun", "fencer_id": "136338", "club": "H3", "rating": "U\u00a0", "rating_earned": "\u00a0"}, {"place": "32", "fencer_name": "\u00a0\u00a0Yen, Josh", "fencer_id": "106954", "club": "MISSION FC", "rating": "C2018\u00a0", "rating_earned": "\u00a0"}, {"place": "33", "fencer_name": "\u00a0\u00a0Szigeti, Alec", "fencer_id": "132009", "club": "SBFC", "rating": "U\u00a0", "rating_earned": "\u00a0"}, {"place": "34", "fencer_name": "\u00a0\u00a0Kurtz, Christopher", "fencer_id": "131837", "club": "UNAT", "rating": "E2017\u00a0", "rating_earned": "\u00a0"}, {"place": "35", "fencer_name": "\u00a0\u00a0Elder, John", "fencer_id": "105630", "club": "AFB", "rating": "U\u00a0", "rating_earned": "\u00a0"}]}, {"event_name": ["\n", "C & Under Senior Men's Saber:\u00a0\u00a0\u00a0\n24 Competitors, a C1 Event\n\u00a0\u00a0\u00a0\u00a0\u00a0\u00a0\n", "\n"], "event_id": "159031", "fencers": [{"place": "1", "fencer_name": "\u00a0\u00a0Moskowitz, Mason", "fencer_id": "105409", "club": "KSA", "rating": "E2018\u00a0", "rating_earned": "C2018\u00a0"}, {"place": "2", "fencer_name": "\u00a0\u00a0Tian, Albert", "fencer_id": "144298", "club": "MISSION FC", "rating": "D2018\u00a0", "rating_earned": "\u00a0"}, {"place": "3", "fencer_name": "\u00a0\u00a0Yen, Josh", "fencer_id": "106954", "club": "MISSION FC", "rating": "C2018\u00a0", "rating_earned": "\u00a0"}, {"place": "3", "fencer_name": "\u00a0\u00a0Morris, Samuel", "fencer_id": "138298", "club": "H3", "rating": "E2017\u00a0", "rating_earned": "D2018\u00a0"}, {"place": "5", "fencer_name": "\u00a0\u00a0Guzman, R J", "fencer_id": "77767", "club": "INTEGRITY", "rating": "C2017\u00a0", "rating_earned": "\u00a0"}, {"place": "6", "fencer_name": "\u00a0\u00a0Tang, Brendan", "fencer_id": "105161", "club": "AFFA", "rating": "D2015\u00a0", "rating_earned": "\u00a0"}, {"place": "7", "fencer_name": "\u00a0\u00a0Travaglione, Conor", "fencer_id": "136427", "club": "H3", "rating": "C2018\u00a0", "rating_earned": "\u00a0"}, {"place": "8", "fencer_name": "\u00a0\u00a0Deto, Daniel", "fencer_id": "87266", "club": "MISSION FC", "rating": "C2016\u00a0", "rating_earned": "\u00a0"}, {"place": "9", "fencer_name": "\u00a0\u00a0Takemaru, Leo", "fencer_id": "125574", "club": "MISSION FC", "rating": "E2018\u00a0", "rating_earned": "\u00a0"}, {"place": "10", "fencer_name": "\u00a0\u00a0Shanahan, Adam", "fencer_id": "83439", "club": "BOSTON FC", "rating": "C2018\u00a0", "rating_earned": "\u00a0"}, {"place": "11", "fencer_name": "\u00a0\u00a0Szigeti, Alec", "fencer_id": "132009", "club": "SBFC", "rating": "U\u00a0", "rating_earned": "\u00a0"}, {"place": "12", "fencer_name": "\u00a0\u00a0Mudgal, Arjun", "fencer_id": "136338", "club": "H3", "rating": "U\u00a0", "rating_earned": "\u00a0"}, {"place": "13", "fencer_name": "\u00a0\u00a0Bartolo, Domenic", "fencer_id": "119581", "club": "MISSION FC", "rating": "D2018\u00a0", "rating_earned": "\u00a0"}, {"place": "14", "fencer_name": "\u00a0\u00a0Meskill, Adam", "fencer_id": "111317", "club": "MISSION FC", "rating": "U\u00a0", "rating_earned": "\u00a0"}, {"place": "15", "fencer_name": "\u00a0\u00a0Epstein, Henry", "fencer_id": "111360", "club": "INTEGRITY", "rating": "E2017\u00a0", "rating_earned": "\u00a0"}, {"place": "16", "fencer_name": "\u00a0\u00a0Bajaj, Ravi", "fencer_id": "145825", "club": "MISSION FC", "rating": "U\u00a0", "rating_earned": "\u00a0"}, {"place": "17", "fencer_name": "\u00a0\u00a0Kurtz, Christopher", "fencer_id": "131837", "club": "UNAT", "rating": "E2017\u00a0", "rating_earned": "\u00a0"}, {"place": "18", "fencer_name": "\u00a0\u00a0Banting, Owen", "fencer_id": "147592", "club": "H3", "rating": "U\u00a0", "rating_earned": "\u00a0"}, {"place": "19", "fencer_name": "\u00a0\u00a0Kim, Avery", "fencer_id": "129945", "club": "MANHATTAN", "rating": "U\u00a0", "rating_earned": "\u00a0"}, {"place": "20", "fencer_name": "\u00a0\u00a0Wu, Edmond", "fencer_id": "121867", "club": "MANHATTAN", "rating": "D2017\u00a0", "rating_earned": "\u00a0"}, {"place": "21", "fencer_name": "\u00a0\u00a0Elder, John", "fencer_id": "105630", "club": "AFB", "rating": "U\u00a0", "rating_earned": "\u00a0"}, {"place": "22", "fencer_name": "\u00a0\u00a0Dunn, Jack", "fencer_id": "106945", "club": "MISSION FC", "rating": "U\u00a0", "rating_earned": "\u00a0"}, {"place": "23", "fencer_name": "\u00a0\u00a0Liu, Kelly", "fencer_id": "147495", "club": "MISSION FC", "rating": "U\u00a0", "rating_earned": "\u00a0"}, {"place": "24", "fencer_name": "\u00a0\u00a0Cook, Aidan", "fencer_id": "104292", "club": "KSA", "rating": "U\u00a0", "rating_earned": "\u00a0"}]}, {"event_name": ["\n", "Div 1A Senior Women's Epee:\u00a0\u00a0\u00a0\n38 Competitors, a A2 Event\n\u00a0\u00a0\u00a0\u00a0\u00a0\u00a0\n", "\n"], "event_id": "159020", "fencers": [{"place": "1", "fencer_name": "\u00a0\u00a0Choi, Lyla", "fencer_id": "94867", "club": "FAW", "rating": "A2017\u00a0", "rating_earned": "A2018\u00a0"}, {"place": "2", "fencer_name": "\u00a0\u00a0Robles, Elena", "fencer_id": "121821", "club": "MFA", "rating": "B2018\u00a0", "rating_earned": "\u00a0"}, {"place": "3", "fencer_name": "\u00a0\u00a0Igoe, Nirali", "fencer_id": "87184", "club": "POFC", "rating": "B2017\u00a0", "rating_earned": "B2018\u00a0"}, {"place": "3", "fencer_name": "\u00a0\u00a0O'Reilly, Meghan", "fencer_id": "78705", "club": "OLYMPIAFC", "rating": "A2016\u00a0", "rating_earned": "\u00a0"}, {"place": "5", "fencer_name": "\u00a0\u00a0Marchant, Sandra", "fencer_id": "52059", "club": "PFC", "rating": "A2014\u00a0", "rating_earned": "\u00a0"}, {"place": "6", "fencer_name": "\u00a0\u00a0Kang, Dahyun", "fencer_id": "132790", "club": "UNAT", "rating": "C2017\u00a0", "rating_earned": "C2018\u00a0"}, {"place": "7", "fencer_name": "\u00a0\u00a0Zhang, Maya", "fencer_id": "121535", "club": "MEDEO FC", "rating": "D2018\u00a0", "rating_earned": "C2018\u00a0"}, {"place": "8", "fencer_name": "\u00a0\u00a0Duffy, Julia", "fencer_id": "122218", "club": "MISSION FC", "rating": "B2016\u00a0", "rating_earned": "\u00a0"}, {"place": "9", "fencer_name": "\u00a0\u00a0Austin, Tiffini", "fencer_id": "10234", "club": "NJFA", "rating": "C2018\u00a0", "rating_earned": "\u00a0"}, {"place": "10", "fencer_name": "\u00a0\u00a0Zafft, Sharrie", "fencer_id": "113714", "club": "MFA", "rating": "B2018\u00a0", "rating_earned": "\u00a0"}, {"place": "11", "fencer_name": "\u00a0\u00a0Cunningham, Rory", "fencer_id": "87075", "club": "MFA", "rating": "E2017\u00a0", "rating_earned": "E2018\u00a0"}, {"place": "12", "fencer_name": "\u00a0\u00a0Desamours, Sabine", "fencer_id": "74911", "club": "WESTBROOK", "rating": "C2018\u00a0", "rating_earned": "\u00a0"}, {"place": "13", "fencer_name": "\u00a0\u00a0Carey, Michele", "fencer_id": "114439", "club": "BOZEMAN", "rating": "E2018\u00a0", "rating_earned": "\u00a0"}, {"place": "14", "fencer_name": "\u00a0\u00a0Cao, Catherine", "fencer_id": "119275", "club": "MISSION FC", "rating": "D2018\u00a0", "rating_earned": "\u00a0"}, {"place": "15", "fencer_name": "\u00a0\u00a0Shvachkin, Maxine", "fencer_id": "97701", "club": "RFC", "rating": "C2018\u00a0", "rating_earned": "\u00a0"}, {"place": "16", "fencer_name": "\u00a0\u00a0Han, Jaewon", "fencer_id": "115614", "club": "TOP FC", "rating": "D2018\u00a0", "rating_earned": "\u00a0"}, {"place": "17", "fencer_name": "\u00a0\u00a0Yoon, Julia", "fencer_id": "113509", "club": "TIGERZ FA", "rating": "C2017\u00a0", "rating_earned": "\u00a0"}, {"place": "18", "fencer_name": "\u00a0\u00a0Shoates, Jacqueline", "fencer_id": "120921", "club": "WESTBROOK", "rating": "C2017\u00a0", "rating_earned": "\u00a0"}, {"place": "19", "fencer_name": "\u00a0\u00a0Lin, Anna", "fencer_id": "125530", "club": "ISLAND NY", "rating": "B2017\u00a0", "rating_earned": "\u00a0"}, {"place": "20", "fencer_name": "\u00a0\u00a0Peralta-Virtue, Kamilla", "fencer_id": "104000", "club": "BSF", "rating": "D2018\u00a0", "rating_earned": "\u00a0"}, {"place": "21", "fencer_name": "\u00a0\u00a0Ni, Emma", "fencer_id": "127533", "club": "MEDEO FC", "rating": "C2018\u00a0", "rating_earned": "\u00a0"}, {"place": "22", "fencer_name": "\u00a0\u00a0Biggs, Amelia", "fencer_id": "77412", "club": "RIFAC", "rating": "C2018\u00a0", "rating_earned": "\u00a0"}, {"place": "23", "fencer_name": "\u00a0\u00a0Li, Annie", "fencer_id": "136865", "club": "LIFC", "rating": "U\u00a0", "rating_earned": "\u00a0"}, {"place": "24", "fencer_name": "\u00a0\u00a0Chan, Elizabeth", "fencer_id": "127433", "club": "MEDEO FC", "rating": "D2018\u00a0", "rating_earned": "\u00a0"}, {"place": "25", "fencer_name": "\u00a0\u00a0Kowalsky, Rachel", "fencer_id": "144286", "club": "H3", "rating": "D2018\u00a0", "rating_earned": "\u00a0"}, {"place": "26", "fencer_name": "\u00a0\u00a0Groening, Joanne", "fencer_id": "10804", "club": "NSFC", "rating": "C2016\u00a0", "rating_earned": "\u00a0"}, {"place": "27", "fencer_name": "\u00a0\u00a0Shi, Angela", "fencer_id": "115150", "club": "PREMIER FC", "rating": "D2017\u00a0", "rating_earned": "\u00a0"}, {"place": "28", "fencer_name": "\u00a0\u00a0Douglas, Julia", "fencer_id": "88591", "club": "RIFAC", "rating": "E2017\u00a0", "rating_earned": "\u00a0"}, {"place": "29", "fencer_name": "\u00a0\u00a0Mueller, Victoria", "fencer_id": "62062", "club": "RIFAC", "rating": "D2018\u00a0", "rating_earned": "\u00a0"}, {"place": "30", "fencer_name": "\u00a0\u00a0Saal, Anna", "fencer_id": "116222", "club": "RIFAC", "rating": "D2018\u00a0", "rating_earned": "\u00a0"}, {"place": "31", "fencer_name": "\u00a0\u00a0Huh, Anna", "fencer_id": "151588", "club": "TOP FC", "rating": "E2018\u00a0", "rating_earned": "\u00a0"}, {"place": "32", "fencer_name": "\u00a0\u00a0Patel, Viha", "fencer_id": "121519", "club": "RIFAC", "rating": "E2018\u00a0", "rating_earned": "\u00a0"}, {"place": "33", "fencer_name": "\u00a0\u00a0Leute, Allison", "fencer_id": "106947", "club": "MISSION FC", "rating": "U\u00a0", "rating_earned": "\u00a0"}, {"place": "34", "fencer_name": "\u00a0\u00a0Becchina, Olivia", "fencer_id": "141007", "club": "MISSION FC", "rating": "U\u00a0", "rating_earned": "\u00a0"}, {"place": "35", "fencer_name": "\u00a0\u00a0Herbert, Brooke", "fencer_id": "106948", "club": "MISSION FC", "rating": "U\u00a0", "rating_earned": "\u00a0"}, {"place": "36", "fencer_name": "\u00a0\u00a0Chan, Christine", "fencer_id": "98102", "club": "MEDEO FC", "rating": "U\u00a0", "rating_earned": "\u00a0"}, {"place": "37", "fencer_name": "\u00a0\u00a0Nicou, Nicole", "fencer_id": "126024", "club": "H3", "rating": "E2018\u00a0", "rating_earned": "\u00a0"}, {"place": "38", "fencer_name": "\u00a0\u00a0Murrell, Jessica", "fencer_id": "144194", "club": "H3", "rating": "U\u00a0", "rating_earned": "\u00a0"}]}, {"event_name": ["\n", "C & Under Senior Women's Epee:\u00a0\u00a0\u00a0\n29 Competitors, a C2 Event\n\u00a0\u00a0\u00a0\u00a0\u00a0\u00a0\n", "\n"], "event_id": "159021", "fencers": [{"place": "1", "fencer_name": "\u00a0\u00a0Kim, Diane", "fencer_id": "136454", "club": "TOP FC", "rating": "C2018\u00a0", "rating_earned": "\u00a0"}, {"place": "2", "fencer_name": "\u00a0\u00a0Han, Jaewon", "fencer_id": "115614", "club": "TOP FC", "rating": "D2018\u00a0", "rating_earned": "\u00a0"}, {"place": "3", "fencer_name": "\u00a0\u00a0Smuk, Daria", "fencer_id": "81493", "club": "RIFAC", "rating": "E2018\u00a0", "rating_earned": "D2018\u00a0"}, {"place": "3", "fencer_name": "\u00a0\u00a0Cao, Catherine", "fencer_id": "119275", "club": "MISSION FC", "rating": "D2018\u00a0", "rating_earned": "\u00a0"}, {"place": "5", "fencer_name": "\u00a0\u00a0Chan, Elizabeth", "fencer_id": "127433", "club": "MEDEO FC", "rating": "D2018\u00a0", "rating_earned": "\u00a0"}, {"place": "6", "fencer_name": "\u00a0\u00a0Desamours, Sabine", "fencer_id": "74911", "club": "WESTBROOK", "rating": "C2018\u00a0", "rating_earned": "\u00a0"}, {"place": "7", "fencer_name": "\u00a0\u00a0Biggs, Amelia", "fencer_id": "77412", "club": "RIFAC", "rating": "C2018\u00a0", "rating_earned": "\u00a0"}, {"place": "8", "fencer_name": "\u00a0\u00a0Groening, Joanne", "fencer_id": "10804", "club": "NSFC", "rating": "C2016\u00a0", "rating_earned": "\u00a0"}, {"place": "9", "fencer_name": "\u00a0\u00a0Chen, Alina", "fencer_id": "120075", "club": "H3", "rating": "E2017\u00a0", "rating_earned": "\u00a0"}, {"place": "10", "fencer_name": "\u00a0\u00a0Hodges, Grace", "fencer_id": "147176", "club": "RFC", "rating": "U\u00a0", "rating_earned": "\u00a0"}, {"place": "11", "fencer_name": "\u00a0\u00a0Advincula, Anabella", "fencer_id": "138143", "club": "FC", "rating": "C2017\u00a0", "rating_earned": "\u00a0"}, {"place": "12", "fencer_name": "\u00a0\u00a0Pino, Jennifer", "fencer_id": "125762", "club": "H3", "rating": "D2017\u00a0", "rating_earned": "\u00a0"}, {"place": "13", "fencer_name": "\u00a0\u00a0Shoates, Jacqueline", "fencer_id": "120921", "club": "WESTBROOK", "rating": "C2017\u00a0", "rating_earned": "\u00a0"}, {"place": "14", "fencer_name": "\u00a0\u00a0Huh, Anna", "fencer_id": "151588", "club": "TOP FC", "rating": "E2018\u00a0", "rating_earned": "\u00a0"}, {"place": "15", "fencer_name": "\u00a0\u00a0Douglas, Julia", "fencer_id": "88591", "club": "RIFAC", "rating": "E2017\u00a0", "rating_earned": "\u00a0"}, {"place": "16", "fencer_name": "\u00a0\u00a0Ni, Emma", "fencer_id": "127533", "club": "MEDEO FC", "rating": "C2018\u00a0", "rating_earned": "\u00a0"}, {"place": "17", "fencer_name": "\u00a0\u00a0Kowalsky, Rachel", "fencer_id": "144286", "club": "H3", "rating": "D2018\u00a0", "rating_earned": "\u00a0"}, {"place": "18", "fencer_name": "\u00a0\u00a0Herbert, Brooke", "fencer_id": "106948", "club": "MISSION FC", "rating": "U\u00a0", "rating_earned": "\u00a0"}, {"place": "19", "fencer_name": "\u00a0\u00a0Saal, Anna", "fencer_id": "116222", "club": "RIFAC", "rating": "D2018\u00a0", "rating_earned": "\u00a0"}, {"place": "20", "fencer_name": "\u00a0\u00a0Jing, Alexandra", "fencer_id": "115637", "club": "MFA", "rating": "U\u00a0", "rating_earned": "\u00a0"}, {"place": "21", "fencer_name": "\u00a0\u00a0Nicou, Nicole", "fencer_id": "126024", "club": "H3", "rating": "E2018\u00a0", "rating_earned": "\u00a0"}, {"place": "22", "fencer_name": "\u00a0\u00a0Carey, Michele", "fencer_id": "114439", "club": "BOZEMAN", "rating": "E2018\u00a0", "rating_earned": "\u00a0"}, {"place": "23", "fencer_name": "\u00a0\u00a0Smith, Grace", "fencer_id": "122637", "club": "MISSION FC", "rating": "U\u00a0", "rating_earned": "\u00a0"}, {"place": "24", "fencer_name": "\u00a0\u00a0Patel, Viha", "fencer_id": "121519", "club": "RIFAC", "rating": "E2018\u00a0", "rating_earned": "\u00a0"}, {"place": "25", "fencer_name": "\u00a0\u00a0Chan, Christine", "fencer_id": "98102", "club": "MEDEO FC", "rating": "U\u00a0", "rating_earned": "\u00a0"}, {"place": "26", "fencer_name": "\u00a0\u00a0Becchina, Olivia", "fencer_id": "141007", "club": "MISSION FC", "rating": "U\u00a0", "rating_earned": "\u00a0"}, {"place": "27", "fencer_name": "\u00a0\u00a0Robert, Lily", "fencer_id": "145181", "club": "H3", "rating": "U\u00a0", "rating_earned": "\u00a0"}, {"place": "27", "fencer_name": "\u00a0\u00a0Cunningham, Rory", "fencer_id": "87075", "club": "MFA", "rating": "E2017\u00a0", "rating_earned": "\u00a0"}, {"place": "29", "fencer_name": "\u00a0\u00a0Leute, Allison", "fencer_id": "106947", "club": "MISSION FC", "rating": "U\u00a0", "rating_earned": "\u00a0"}]}, {"event_name": ["\n", "Div 1A Senior Women's Foil:\u00a0\u00a0\u00a0\n47 Competitors, a A2 Event\n\u00a0\u00a0\u00a0\u00a0\u00a0\u00a0\n", "\n"], "event_id": "159022", "fencers": [{"place": "1", "fencer_name": "\u00a0\u00a0Lam, Justina", "fencer_id": "90847", "club": "FC", "rating": "A2018\u00a0", "rating_earned": "\u00a0"}, {"place": "2", "fencer_name": "\u00a0\u00a0Koo, Haley", "fencer_id": "88907", "club": "GUTKOVSKIY", "rating": "A2018\u00a0", "rating_earned": "\u00a0"}, {"place": "3", "fencer_name": "\u00a0\u00a0Kasi, Anisha", "fencer_id": "85944", "club": "GUTKOVSKIY", "rating": "A2018\u00a0", "rating_earned": "\u00a0"}, {"place": "3", "fencer_name": "\u00a0\u00a0Mak, Tinney", "fencer_id": "92139", "club": "PREMIER FC", "rating": "A2018\u00a0", "rating_earned": "\u00a0"}, {"place": "5", "fencer_name": "\u00a0\u00a0Weintraub, Rei", "fencer_id": "87062", "club": "FC", "rating": "A2018\u00a0", "rating_earned": "\u00a0"}, {"place": "6", "fencer_name": "\u00a0\u00a0Kim, Lauren Hyomin", "fencer_id": "86791", "club": "FC", "rating": "B2018\u00a0", "rating_earned": "\u00a0"}, {"place": "7", "fencer_name": "\u00a0\u00a0Shen, Jasmine", "fencer_id": "104314", "club": "DURKAN FA", "rating": "B2017\u00a0", "rating_earned": "\u00a0"}, {"place": "8", "fencer_name": "\u00a0\u00a0Balch, Julia", "fencer_id": "107213", "club": "FAIRFIELD", "rating": "B2017\u00a0", "rating_earned": "\u00a0"}, {"place": "9", "fencer_name": "\u00a0\u00a0Chusid, Renata", "fencer_id": "88443", "club": "GUTKOVSKIY", "rating": "A2018\u00a0", "rating_earned": "\u00a0"}, {"place": "10", "fencer_name": "\u00a0\u00a0Marotta, Veronica", "fencer_id": "60556", "club": "FC", "rating": "B2016\u00a0", "rating_earned": "\u00a0"}, {"place": "11", "fencer_name": "\u00a0\u00a0Ahn, Isabella", "fencer_id": "102824", "club": "FC", "rating": "B2018\u00a0", "rating_earned": "\u00a0"}, {"place": "12", "fencer_name": "\u00a0\u00a0Breker, Anika", "fencer_id": "66208", "club": "RIFAC", "rating": "B2018\u00a0", "rating_earned": "\u00a0"}, {"place": "13", "fencer_name": "\u00a0\u00a0Yugov, Elizabeth", "fencer_id": "71821", "club": "VFC", "rating": "C2017\u00a0", "rating_earned": "\u00a0"}, {"place": "14", "fencer_name": "\u00a0\u00a0Stewart, Isabella", "fencer_id": "99881", "club": "FAW", "rating": "B2018\u00a0", "rating_earned": "\u00a0"}, {"place": "15", "fencer_name": "\u00a0\u00a0Zheng, Vivian", "fencer_id": "98324", "club": "RFC", "rating": "B2018\u00a0", "rating_earned": "\u00a0"}, {"place": "16", "fencer_name": "\u00a0\u00a0Raso, Sofia", "fencer_id": "86804", "club": "FC", "rating": "C2018\u00a0", "rating_earned": "\u00a0"}, {"place": "17", "fencer_name": "\u00a0\u00a0Stamos, Maria", "fencer_id": "82068", "club": "MANHATTAN", "rating": "A2017\u00a0", "rating_earned": "\u00a0"}, {"place": "18", "fencer_name": "\u00a0\u00a0Shortall, Samantha", "fencer_id": "96841", "club": "OLYMPIAFC", "rating": "C2018\u00a0", "rating_earned": "\u00a0"}, {"place": "19", "fencer_name": "\u00a0\u00a0Holle, Aviella", "fencer_id": "100166", "club": "5T FC", "rating": "C2018\u00a0", "rating_earned": "\u00a0"}, {"place": "20", "fencer_name": "\u00a0\u00a0Ahn, Gabriella", "fencer_id": "102825", "club": "FC", "rating": "A2018\u00a0", "rating_earned": "\u00a0"}, {"place": "21", "fencer_name": "\u00a0\u00a0Hooshi, Erica", "fencer_id": "136241", "club": "5T FC", "rating": "D2018\u00a0", "rating_earned": "\u00a0"}, {"place": "22", "fencer_name": "\u00a0\u00a0Lee, Madison", "fencer_id": "90372", "club": "FAIRFIELD", "rating": "B2017\u00a0", "rating_earned": "\u00a0"}, {"place": "23", "fencer_name": "\u00a0\u00a0Lee, Allison", "fencer_id": "86041", "club": "PREMIER FC", "rating": "A2017\u00a0", "rating_earned": "\u00a0"}, {"place": "24", "fencer_name": "\u00a0\u00a0Kim, Lauren C", "fencer_id": "90011", "club": "TOP FC", "rating": "B2017\u00a0", "rating_earned": "\u00a0"}, {"place": "25", "fencer_name": "\u00a0\u00a0Jing, Alexandra", "fencer_id": "115637", "club": "MFA", "rating": "B2018\u00a0", "rating_earned": "\u00a0"}, {"place": "26", "fencer_name": "\u00a0\u00a0Koo, Rachel", "fencer_id": "104100", "club": "GUTKOVSKIY", "rating": "B2017\u00a0", "rating_earned": "\u00a0"}, {"place": "27", "fencer_name": "\u00a0\u00a0Ye, Eileen", "fencer_id": "104116", "club": "MANHATTAN", "rating": "C2017\u00a0", "rating_earned": "\u00a0"}, {"place": "28", "fencer_name": "\u00a0\u00a0Patel, Anika", "fencer_id": "88545", "club": "FREEHOLD", "rating": "C2017\u00a0", "rating_earned": "\u00a0"}, {"place": "29", "fencer_name": "\u00a0\u00a0Davidson, Sammy", "fencer_id": "105044", "club": "FAIRFIELD", "rating": "D2018\u00a0", "rating_earned": "\u00a0"}, {"place": "30", "fencer_name": "\u00a0\u00a0McGillion-Moore, Katie", "fencer_id": "117637", "club": "FAIRFIELD", "rating": "C2017\u00a0", "rating_earned": "\u00a0"}, {"place": "31", "fencer_name": "\u00a0\u00a0Hu, Ally", "fencer_id": "122574", "club": "MISSION FC", "rating": "E2016\u00a0", "rating_earned": "\u00a0"}, {"place": "32", "fencer_name": "\u00a0\u00a0Shalansky, Julia", "fencer_id": "55050", "club": "RIFAC", "rating": "B2017\u00a0", "rating_earned": "\u00a0"}, {"place": "33", "fencer_name": "\u00a0\u00a0Shang, Andrea", "fencer_id": "114549", "club": "GOLD", "rating": "C2018\u00a0", "rating_earned": "\u00a0"}, {"place": "34", "fencer_name": "\u00a0\u00a0Xu, Christine", "fencer_id": "94125", "club": "FC", "rating": "D2017\u00a0", "rating_earned": "\u00a0"}, {"place": "35", "fencer_name": "\u00a0\u00a0McDonald, Alexandra", "fencer_id": "83392", "club": "RIFAC", "rating": "B2018\u00a0", "rating_earned": "\u00a0"}, {"place": "36", "fencer_name": "\u00a0\u00a0Sadan, Jordan", "fencer_id": "146273", "club": "PREMIER FC", "rating": "E2018\u00a0", "rating_earned": "\u00a0"}, {"place": "37", "fencer_name": "\u00a0\u00a0Shaw, Kayla", "fencer_id": "129405", "club": "RFC", "rating": "D2018\u00a0", "rating_earned": "\u00a0"}, {"place": "38", "fencer_name": "\u00a0\u00a0Zavala-Arbelaez, Ivanna", "fencer_id": "119335", "club": "MISSION FC", "rating": "E2016\u00a0", "rating_earned": "\u00a0"}, {"place": "39", "fencer_name": "\u00a0\u00a0O'Neill, Kathleen", "fencer_id": "123264", "club": "H3", "rating": "E2018\u00a0", "rating_earned": "\u00a0"}, {"place": "40", "fencer_name": "\u00a0\u00a0Pino, Jennifer", "fencer_id": "125762", "club": "H3", "rating": "E2017\u00a0", "rating_earned": "\u00a0"}, {"place": "41", "fencer_name": "\u00a0\u00a0O'Brien, Sandra", "fencer_id": "110927", "club": "MISSION FC", "rating": "E2016\u00a0", "rating_earned": "\u00a0"}, {"place": "42", "fencer_name": "\u00a0\u00a0Wu, Irene", "fencer_id": "115525", "club": "OLYMPIAFC", "rating": "D2017\u00a0", "rating_earned": "\u00a0"}, {"place": "43", "fencer_name": "\u00a0\u00a0Devereaux, Kate", "fencer_id": "117114", "club": "H3", "rating": "D2015\u00a0", "rating_earned": "\u00a0"}, {"place": "44", "fencer_name": "\u00a0\u00a0Nicou, Melina", "fencer_id": "126524", "club": "H3", "rating": "U\u00a0", "rating_earned": "\u00a0"}, {"place": "45", "fencer_name": "\u00a0\u00a0Becchina, Claire", "fencer_id": "129890", "club": "MISSION FC", "rating": "U\u00a0", "rating_earned": "\u00a0"}, {"place": "46", "fencer_name": "\u00a0\u00a0Bajaj, Jasmine", "fencer_id": "123960", "club": "MISSION FC", "rating": "U\u00a0", "rating_earned": "\u00a0"}, {"place": "46", "fencer_name": "\u00a0\u00a0Herbert, Lauren", "fencer_id": "106949", "club": "MISSION FC", "rating": "U\u00a0", "rating_earned": "\u00a0"}]}, {"event_name": ["\n", "C & Under Senior Women's Foil:\u00a0\u00a0\u00a0\n26 Competitors, a C2 Event\n\u00a0\u00a0\u00a0\u00a0\u00a0\u00a0\n", "\n"], "event_id": "159023", "fencers": [{"place": "1", "fencer_name": "\u00a0\u00a0Hu, Ally", "fencer_id": "122574", "club": "MISSION FC", "rating": "E2016\u00a0", "rating_earned": "C2018\u00a0"}, {"place": "2", "fencer_name": "\u00a0\u00a0Xu, Christine", "fencer_id": "94125", "club": "FC", "rating": "D2017\u00a0", "rating_earned": "D2018\u00a0"}, {"place": "3", "fencer_name": "\u00a0\u00a0Sadan, Jordan", "fencer_id": "146273", "club": "PREMIER FC", "rating": "E2018\u00a0", "rating_earned": "D2018\u00a0"}, {"place": "3", "fencer_name": "\u00a0\u00a0Hooshi, Erica", "fencer_id": "136241", "club": "5T FC", "rating": "D2018\u00a0", "rating_earned": "\u00a0"}, {"place": "5", "fencer_name": "\u00a0\u00a0Holle, Aviella", "fencer_id": "100166", "club": "5T FC", "rating": "C2018\u00a0", "rating_earned": "\u00a0"}, {"place": "6", "fencer_name": "\u00a0\u00a0McGillion-Moore, Katie", "fencer_id": "117637", "club": "FAIRFIELD", "rating": "C2017\u00a0", "rating_earned": "\u00a0"}, {"place": "7", "fencer_name": "\u00a0\u00a0Saxena, Sejal", "fencer_id": "65275", "club": "GUTKOVSKIY", "rating": "D2018\u00a0", "rating_earned": "\u00a0"}, {"place": "8", "fencer_name": "\u00a0\u00a0Davidson, Sammy", "fencer_id": "105044", "club": "FAIRFIELD", "rating": "D2018\u00a0", "rating_earned": "\u00a0"}, {"place": "9", "fencer_name": "\u00a0\u00a0Du, Hannah", "fencer_id": "119396", "club": "MOE FC", "rating": "E2018\u00a0", "rating_earned": "\u00a0"}, {"place": "10", "fencer_name": "\u00a0\u00a0Becker, Elena", "fencer_id": "140169", "club": "UNAT", "rating": "D2017\u00a0", "rating_earned": "\u00a0"}, {"place": "11", "fencer_name": "\u00a0\u00a0Shen, Sophia", "fencer_id": "93161", "club": "DURKAN FA", "rating": "D2018\u00a0", "rating_earned": "\u00a0"}, {"place": "12", "fencer_name": "\u00a0\u00a0Lubin, Tori", "fencer_id": "120061", "club": "FAIRFIELD", "rating": "E2018\u00a0", "rating_earned": "\u00a0"}, {"place": "13", "fencer_name": "\u00a0\u00a0O'Brien, Sandra", "fencer_id": "110927", "club": "MISSION FC", "rating": "E2016\u00a0", "rating_earned": "\u00a0"}, {"place": "14", "fencer_name": "\u00a0\u00a0Devereaux, Kate", "fencer_id": "117114", "club": "H3", "rating": "D2015\u00a0", "rating_earned": "\u00a0"}, {"place": "15", "fencer_name": "\u00a0\u00a0Zimbalist, Lila", "fencer_id": "130021", "club": "GUTKOVSKIY", "rating": "E2018\u00a0", "rating_earned": "\u00a0"}, {"place": "16", "fencer_name": "\u00a0\u00a0Liu, Carolyn", "fencer_id": "112390", "club": "MISSION FC", "rating": "U\u00a0", "rating_earned": "\u00a0"}, {"place": "17", "fencer_name": "\u00a0\u00a0Becchina, Claire", "fencer_id": "129890", "club": "MISSION FC", "rating": "U\u00a0", "rating_earned": "\u00a0"}, {"place": "18", "fencer_name": "\u00a0\u00a0O'Neill, Kathleen", "fencer_id": "123264", "club": "H3", "rating": "E2018\u00a0", "rating_earned": "\u00a0"}, {"place": "19", "fencer_name": "\u00a0\u00a0Zavala-Arbelaez, Ivanna", "fencer_id": "119335", "club": "MISSION FC", "rating": "E2016\u00a0", "rating_earned": "\u00a0"}, {"place": "20", "fencer_name": "\u00a0\u00a0Bajaj, Jasmine", "fencer_id": "123960", "club": "MISSION FC", "rating": "U\u00a0", "rating_earned": "\u00a0"}, {"place": "21", "fencer_name": "\u00a0\u00a0Jacinto, Jenna", "fencer_id": "145945", "club": "H3", "rating": "U\u00a0", "rating_earned": "\u00a0"}, {"place": "22", "fencer_name": "\u00a0\u00a0Nicou, Melina", "fencer_id": "126524", "club": "H3", "rating": "U\u00a0", "rating_earned": "\u00a0"}, {"place": "23", "fencer_name": "\u00a0\u00a0Rocca, Josie", "fencer_id": "124800", "club": "CANDLEWOOD", "rating": "E2018\u00a0", "rating_earned": "\u00a0"}, {"place": "24", "fencer_name": "\u00a0\u00a0Villanueva, Flor", "fencer_id": "145198", "club": "H3", "rating": "U\u00a0", "rating_earned": "\u00a0"}, {"place": "25", "fencer_name": "\u00a0\u00a0Silver, Anna", "fencer_id": "149883", "club": "H3", "rating": "U\u00a0", "rating_earned": "\u00a0"}, {"place": "26", "fencer_name": "\u00a0\u00a0Herbert, Lauren", "fencer_id": "106949", "club": "MISSION FC", "rating": "U\u00a0", "rating_earned": "\u00a0"}]}, {"event_name": ["\n", "Div 1A Senior Women's Saber:\u00a0\u00a0\u00a0\n30 Competitors, a A2 Event\n\u00a0\u00a0\u00a0\u00a0\u00a0\u00a0\n", "\n"], "event_id": "159024", "fencers": [{"place": "1", "fencer_name": "\u00a0\u00a0Hoffman, Ilsa", "fencer_id": "126695", "club": "KSA", "rating": "B2018\u00a0", "rating_earned": "A2018\u00a0"}, {"place": "2", "fencer_name": "\u00a0\u00a0Wong, Kristen", "fencer_id": "68537", "club": "UNAT", "rating": "A2016\u00a0", "rating_earned": "\u00a0"}, {"place": "3", "fencer_name": "\u00a0\u00a0Weber, Juliana", "fencer_id": "105096", "club": "MEDEO FC", "rating": "D2017\u00a0", "rating_earned": "B2018\u00a0"}, {"place": "3", "fencer_name": "\u00a0\u00a0Becchina, Bridget", "fencer_id": "118928", "club": "MISSION FC", "rating": "B2017\u00a0", "rating_earned": "B2018\u00a0"}, {"place": "5", "fencer_name": "\u00a0\u00a0Palmer, Kristen", "fencer_id": "102820", "club": "WESTBROOK", "rating": "B2018\u00a0", "rating_earned": "\u00a0"}, {"place": "6", "fencer_name": "\u00a0\u00a0Hilado, Sarah", "fencer_id": "111941", "club": "SHERIDAN", "rating": "B2018\u00a0", "rating_earned": "\u00a0"}, {"place": "7", "fencer_name": "\u00a0\u00a0Faucher, Erin", "fencer_id": "81485", "club": "RIFAC", "rating": "C2017\u00a0", "rating_earned": "C2018\u00a0"}, {"place": "8", "fencer_name": "\u00a0\u00a0Hassan, Aziza", "fencer_id": "11734", "club": "WESTBROOK", "rating": "A2014\u00a0", "rating_earned": "\u00a0"}, {"place": "9", "fencer_name": "\u00a0\u00a0Kalina, Rachel", "fencer_id": "21498", "club": "SHERIDAN", "rating": "B2017\u00a0", "rating_earned": "\u00a0"}, {"place": "10", "fencer_name": "\u00a0\u00a0Sathyanath, Kailing", "fencer_id": "143879", "club": "INTEGRITY", "rating": "C2018\u00a0", "rating_earned": "\u00a0"}, {"place": "11", "fencer_name": "\u00a0\u00a0Tzou, Alexandra", "fencer_id": "131050", "club": "SHERIDAN", "rating": "D2018\u00a0", "rating_earned": "\u00a0"}, {"place": "12", "fencer_name": "\u00a0\u00a0Oxenstierna, Carolina", "fencer_id": "99948", "club": "SFC", "rating": "C2017\u00a0", "rating_earned": "\u00a0"}, {"place": "13", "fencer_name": "\u00a0\u00a0Seck, Chejsa-Kaili", "fencer_id": "97351", "club": "WESTBROOK", "rating": "B2017\u00a0", "rating_earned": "\u00a0"}, {"place": "14", "fencer_name": "\u00a0\u00a0Chen, Erica", "fencer_id": "111859", "club": "H3", "rating": "C2017\u00a0", "rating_earned": "\u00a0"}, {"place": "15", "fencer_name": "\u00a0\u00a0Cappello, Lauren", "fencer_id": "124900", "club": "MISSION FC", "rating": "C2018\u00a0", "rating_earned": "\u00a0"}, {"place": "16", "fencer_name": "\u00a0\u00a0Turnof, Kayla", "fencer_id": "77013", "club": "AFFA", "rating": "E2018\u00a0", "rating_earned": "\u00a0"}, {"place": "17", "fencer_name": "\u00a0\u00a0Miller, Stephanie", "fencer_id": "119181", "club": "MISSION FC", "rating": "C2017\u00a0", "rating_earned": "\u00a0"}, {"place": "18", "fencer_name": "\u00a0\u00a0Valadez, Emily", "fencer_id": "106733", "club": "MISSION FC", "rating": "C2018\u00a0", "rating_earned": "\u00a0"}, {"place": "19", "fencer_name": "\u00a0\u00a0Waye, Elizabeth", "fencer_id": "42306", "club": "RFC", "rating": "E2017\u00a0", "rating_earned": "\u00a0"}, {"place": "20", "fencer_name": "\u00a0\u00a0Kuznetsova, Nastassja", "fencer_id": "130763", "club": "MORRIS FC", "rating": "C2017\u00a0", "rating_earned": "\u00a0"}, {"place": "21", "fencer_name": "\u00a0\u00a0Delucia, Nicole", "fencer_id": "106950", "club": "MISSION FC", "rating": "U\u00a0", "rating_earned": "\u00a0"}, {"place": "22", "fencer_name": "\u00a0\u00a0Tao, Hannah", "fencer_id": "134749", "club": "AFFA", "rating": "E2018\u00a0", "rating_earned": "\u00a0"}, {"place": "23", "fencer_name": "\u00a0\u00a0Newell, Alexia", "fencer_id": "133724", "club": "AFFA", "rating": "C2018\u00a0", "rating_earned": "\u00a0"}, {"place": "24", "fencer_name": "\u00a0\u00a0Garibian, Emma", "fencer_id": "85306", "club": "LILOV FENC", "rating": "D2018\u00a0", "rating_earned": "\u00a0"}, {"place": "25", "fencer_name": "\u00a0\u00a0Lettieri, Sophia", "fencer_id": "111070", "club": "H3", "rating": "E2017\u00a0", "rating_earned": "\u00a0"}, {"place": "26", "fencer_name": "\u00a0\u00a0Nielsen, Dianna", "fencer_id": "151360", "club": "MISSION FC", "rating": "E2018\u00a0", "rating_earned": "\u00a0"}, {"place": "27", "fencer_name": "\u00a0\u00a0Engoran, Emily", "fencer_id": "145182", "club": "H3", "rating": "U\u00a0", "rating_earned": "\u00a0"}, {"place": "28", "fencer_name": "\u00a0\u00a0Mays, Hailey", "fencer_id": "151193", "club": "MISSION FC", "rating": "U\u00a0", "rating_earned": "\u00a0"}, {"place": "28", "fencer_name": "\u00a0\u00a0Wheeler, Kira", "fencer_id": "141822", "club": "KSA", "rating": "U\u00a0", "rating_earned": "\u00a0"}, {"place": "30", "fencer_name": "\u00a0\u00a0Obedin, Tori", "fencer_id": "113204", "club": "MISSION FC", "rating": "U\u00a0", "rating_earned": "\u00a0"}]}, {"event_name": ["\n", "C & Under Senior Women's Saber:\u00a0\u00a0\u00a0\n24 Competitors, a C1 Event\n\u00a0\u00a0\u00a0\u00a0\u00a0\u00a0\n", "\n"], "event_id": "159025", "fencers": [{"place": "1", "fencer_name": "\u00a0\u00a0Hoffman, Ilsa", "fencer_id": "126695", "club": "KSA", "rating": "B2018\u00a0", "rating_earned": "\u00a0"}, {"place": "2", "fencer_name": "\u00a0\u00a0Sathyanath, Kailing", "fencer_id": "143879", "club": "INTEGRITY", "rating": "C2018\u00a0", "rating_earned": "\u00a0"}, {"place": "3", "fencer_name": "\u00a0\u00a0Faucher, Erin", "fencer_id": "81485", "club": "RIFAC", "rating": "C2017\u00a0", "rating_earned": "\u00a0"}, {"place": "3", "fencer_name": "\u00a0\u00a0Garibian, Emma", "fencer_id": "85306", "club": "LILOV FENC", "rating": "D2018\u00a0", "rating_earned": "\u00a0"}, {"place": "5", "fencer_name": "\u00a0\u00a0Miller, Stephanie", "fencer_id": "119181", "club": "MISSION FC", "rating": "C2017\u00a0", "rating_earned": "\u00a0"}, {"place": "6", "fencer_name": "\u00a0\u00a0Chen, Erica", "fencer_id": "111859", "club": "H3", "rating": "C2017\u00a0", "rating_earned": "\u00a0"}, {"place": "7", "fencer_name": "\u00a0\u00a0Kuznetsova, Nastassja", "fencer_id": "130763", "club": "MORRIS FC", "rating": "C2017\u00a0", "rating_earned": "\u00a0"}, {"place": "8", "fencer_name": "\u00a0\u00a0Valadez, Emily", "fencer_id": "106733", "club": "MISSION FC", "rating": "C2018\u00a0", "rating_earned": "\u00a0"}, {"place": "9", "fencer_name": "\u00a0\u00a0Cappello, Lauren", "fencer_id": "124900", "club": "MISSION FC", "rating": "C2018\u00a0", "rating_earned": "\u00a0"}, {"place": "10", "fencer_name": "\u00a0\u00a0Tao, Hannah", "fencer_id": "134749", "club": "AFFA", "rating": "E2018\u00a0", "rating_earned": "\u00a0"}, {"place": "11", "fencer_name": "\u00a0\u00a0Kobozeva, Toma", "fencer_id": "82200", "club": "DYNAMOFC", "rating": "D2017\u00a0", "rating_earned": "\u00a0"}, {"place": "12", "fencer_name": "\u00a0\u00a0Matsui, Alynne", "fencer_id": "134175", "club": "MOREHOUSE", "rating": "D2018\u00a0", "rating_earned": "\u00a0"}, {"place": "13", "fencer_name": "\u00a0\u00a0Mackey, Deveraux", "fencer_id": "141656", "club": "WESTBROOK", "rating": "U\u00a0", "rating_earned": "\u00a0"}, {"place": "14", "fencer_name": "\u00a0\u00a0Jassey, Julia", "fencer_id": "127269", "club": "H3", "rating": "U\u00a0", "rating_earned": "\u00a0"}, {"place": "15", "fencer_name": "\u00a0\u00a0Waye, Elizabeth", "fencer_id": "42306", "club": "RFC", "rating": "E2017\u00a0", "rating_earned": "\u00a0"}, {"place": "16", "fencer_name": "\u00a0\u00a0Nielsen, Dianna", "fencer_id": "151360", "club": "MISSION FC", "rating": "E2018\u00a0", "rating_earned": "\u00a0"}, {"place": "17", "fencer_name": "\u00a0\u00a0Chan, Naomi", "fencer_id": "154488", "club": "THRUST", "rating": "U\u00a0", "rating_earned": "\u00a0"}, {"place": "18", "fencer_name": "\u00a0\u00a0Obedin, Tori", "fencer_id": "113204", "club": "MISSION FC", "rating": "U\u00a0", "rating_earned": "\u00a0"}, {"place": "19", "fencer_name": "\u00a0\u00a0Kim, Catherine", "fencer_id": "134022", "club": "H3", "rating": "E2017\u00a0", "rating_earned": "\u00a0"}, {"place": "20", "fencer_name": "\u00a0\u00a0Han, Lauren", "fencer_id": "136707", "club": "MISSION FC", "rating": "U\u00a0", "rating_earned": "\u00a0"}, {"place": "21", "fencer_name": "\u00a0\u00a0Lettieri, Sophia", "fencer_id": "111070", "club": "H3", "rating": "E2017\u00a0", "rating_earned": "\u00a0"}, {"place": "22", "fencer_name": "\u00a0\u00a0Delucia, Nicole", "fencer_id": "106950", "club": "MISSION FC", "rating": "U\u00a0", "rating_earned": "\u00a0"}, {"place": "23", "fencer_name": "\u00a0\u00a0Wheeler, Kira", "fencer_id": "141822", "club": "KSA", "rating": "U\u00a0", "rating_earned": "\u00a0"}, {"place": "24", "fencer_name": "\u00a0\u00a0Mays, Hailey", "fencer_id": "151193", "club": "MISSION FC", "rating": "U\u00a0", "rating_earned": "\u00a0"}]}]}